{
"meta":{"test_sets":[],"test_metrics":[],"learn_metrics":[{"best_value":"Min","name":"RMSE"}],"launch_mode":"Train","parameters":"","iteration_count":1000,"learn_sets":["learn"],"name":"experiment"},
"iterations":[
{"learn":[1986.423679],"iteration":0,"passed_time":0.0004143312224,"remaining_time":0.4139168911},
{"learn":[1948.904477],"iteration":1,"passed_time":0.001032910075,"remaining_time":0.5154221277},
{"learn":[1912.817719],"iteration":2,"passed_time":0.001236700709,"remaining_time":0.410996869},
{"learn":[1878.11634],"iteration":3,"passed_time":0.001441782334,"remaining_time":0.3590038013},
{"learn":[1848.063392],"iteration":4,"passed_time":0.002088361,"remaining_time":0.415583839},
{"learn":[1814.306816],"iteration":5,"passed_time":0.002397483927,"remaining_time":0.3971831707},
{"learn":[1782.989239],"iteration":6,"passed_time":0.002865313791,"remaining_time":0.4064652278},
{"learn":[1755.3309],"iteration":7,"passed_time":0.003222269398,"remaining_time":0.3995614054},
{"learn":[1729.24503],"iteration":8,"passed_time":0.003596225891,"remaining_time":0.3959844287},
{"learn":[1703.713667],"iteration":9,"passed_time":0.003934807621,"remaining_time":0.3895459545},
{"learn":[1680.200349],"iteration":10,"passed_time":0.004505886793,"remaining_time":0.4051201853},
{"learn":[1655.12837],"iteration":11,"passed_time":0.004896343175,"remaining_time":0.4031322548},
{"learn":[1633.002457],"iteration":12,"passed_time":0.005242090857,"remaining_time":0.3979956674},
{"learn":[1612.343996],"iteration":13,"passed_time":0.005643338168,"remaining_time":0.3974522452},
{"learn":[1592.268388],"iteration":14,"passed_time":0.006104919073,"remaining_time":0.4008896858},
{"learn":[1573.056444],"iteration":15,"passed_time":0.006610706682,"remaining_time":0.406558461},
{"learn":[1555.536931],"iteration":16,"passed_time":0.007107203354,"remaining_time":0.4109635822},
{"learn":[1541.952701],"iteration":17,"passed_time":0.00748511782,"remaining_time":0.4083547611},
{"learn":[1524.928856],"iteration":18,"passed_time":0.007909572975,"remaining_time":0.4083837415},
{"learn":[1509.425568],"iteration":19,"passed_time":0.008278195504,"remaining_time":0.4056315797},
{"learn":[1492.571282],"iteration":20,"passed_time":0.008891524392,"remaining_time":0.414514399},
{"learn":[1478.480266],"iteration":21,"passed_time":0.00928564675,"remaining_time":0.4127892055},
{"learn":[1464.56167],"iteration":22,"passed_time":0.009981308086,"remaining_time":0.4239886087},
{"learn":[1452.07691],"iteration":23,"passed_time":0.01064892861,"remaining_time":0.4330564302},
{"learn":[1439.691459],"iteration":24,"passed_time":0.01116805013,"remaining_time":0.4355539551},
{"learn":[1428.111741],"iteration":25,"passed_time":0.01206229414,"remaining_time":0.4518720957},
{"learn":[1416.54386],"iteration":26,"passed_time":0.01297116304,"remaining_time":0.467442283},
{"learn":[1406.08649],"iteration":27,"passed_time":0.01376715771,"remaining_time":0.4779170461},
{"learn":[1395.59807],"iteration":28,"passed_time":0.01458927719,"remaining_time":0.4884892468},
{"learn":[1386.566206],"iteration":29,"passed_time":0.01532048029,"remaining_time":0.4953621961},
{"learn":[1376.379884],"iteration":30,"passed_time":0.01669755406,"remaining_time":0.5219332221},
{"learn":[1367.570638],"iteration":31,"passed_time":0.01734021575,"remaining_time":0.5245415265},
{"learn":[1358.140624],"iteration":32,"passed_time":0.01794721168,"remaining_time":0.5259076878},
{"learn":[1350.005195],"iteration":33,"passed_time":0.01889424633,"remaining_time":0.5368188812},
{"learn":[1343.150044],"iteration":34,"passed_time":0.01973590769,"remaining_time":0.5441471692},
{"learn":[1335.080065],"iteration":35,"passed_time":0.0206750264,"remaining_time":0.5536312624},
{"learn":[1327.699932],"iteration":36,"passed_time":0.0211660651,"remaining_time":0.5508897485},
{"learn":[1320.105128],"iteration":37,"passed_time":0.02172543635,"remaining_time":0.549996573},
{"learn":[1314.541289],"iteration":38,"passed_time":0.02219997517,"remaining_time":0.5470301575},
{"learn":[1308.800126],"iteration":39,"passed_time":0.02258718058,"remaining_time":0.5420923339},
{"learn":[1303.08982],"iteration":40,"passed_time":0.02320417644,"remaining_time":0.5427513465},
{"learn":[1296.187169],"iteration":41,"passed_time":0.02376946465,"remaining_time":0.5421701699},
{"learn":[1290.219055],"iteration":42,"passed_time":0.02441008536,"remaining_time":0.5432663183},
{"learn":[1284.707869],"iteration":43,"passed_time":0.0248804982,"remaining_time":0.5405853701},
{"learn":[1278.726581],"iteration":44,"passed_time":0.02528920346,"remaining_time":0.5366930957},
{"learn":[1273.746098],"iteration":45,"passed_time":0.02602719852,"remaining_time":0.5397814649},
{"learn":[1268.845332],"iteration":46,"passed_time":0.02642098688,"remaining_time":0.5357276701},
{"learn":[1265.375188],"iteration":47,"passed_time":0.02680281732,"remaining_time":0.5315892101},
{"learn":[1259.800425],"iteration":48,"passed_time":0.02736885552,"remaining_time":0.5311792163},
{"learn":[1255.899091],"iteration":49,"passed_time":0.02803493406,"remaining_time":0.5326637471},
{"learn":[1253.182661],"iteration":50,"passed_time":0.02829305733,"remaining_time":0.5264727726},
{"learn":[1248.893979],"iteration":51,"passed_time":0.02897855273,"remaining_time":0.5283013075},
{"learn":[1244.528759],"iteration":52,"passed_time":0.02930688353,"remaining_time":0.5236531831},
{"learn":[1242.120968],"iteration":53,"passed_time":0.0297147148,"remaining_time":0.5205577814},
{"learn":[1238.462975],"iteration":54,"passed_time":0.03035083553,"remaining_time":0.5214825378},
{"learn":[1235.494138],"iteration":55,"passed_time":0.03082187337,"remaining_time":0.5195687226},
{"learn":[1231.688274],"iteration":56,"passed_time":0.03121137076,"remaining_time":0.5163565373},
{"learn":[1228.684865],"iteration":57,"passed_time":0.03239327984,"remaining_time":0.526111545},
{"learn":[1225.624314],"iteration":58,"passed_time":0.03279311016,"remaining_time":0.5230223162},
{"learn":[1221.374429],"iteration":59,"passed_time":0.03320285741,"remaining_time":0.5201780994},
{"learn":[1218.620522],"iteration":60,"passed_time":0.03360372972,"remaining_time":0.5172770854},
{"learn":[1216.196304],"iteration":61,"passed_time":0.03414864307,"remaining_time":0.5166359226},
{"learn":[1213.735809],"iteration":62,"passed_time":0.03469409741,"remaining_time":0.5160058615},
{"learn":[1210.964109],"iteration":63,"passed_time":0.03513451046,"remaining_time":0.5138422155},
{"learn":[1207.157108],"iteration":64,"passed_time":0.03581800588,"remaining_time":0.5152282384},
{"learn":[1204.767227],"iteration":65,"passed_time":0.03631250256,"remaining_time":0.5138769302},
{"learn":[1203.588695],"iteration":66,"passed_time":0.03653846005,"remaining_time":0.5088116899},
{"learn":[1200.694395],"iteration":67,"passed_time":0.03722508045,"remaining_time":0.5102025732},
{"learn":[1197.917682],"iteration":68,"passed_time":0.03786845113,"remaining_time":0.5109496812},
{"learn":[1195.678729],"iteration":69,"passed_time":0.03831478114,"remaining_time":0.5090392352},
{"learn":[1193.636108],"iteration":70,"passed_time":0.03881769477,"remaining_time":0.5079104006},
{"learn":[1191.230617],"iteration":71,"passed_time":0.03923690096,"remaining_time":0.5057200568},
{"learn":[1188.370955],"iteration":72,"passed_time":0.03976152244,"remaining_time":0.5049168672},
{"learn":[1184.572154],"iteration":73,"passed_time":0.04024781018,"remaining_time":0.5036415166},
{"learn":[1182.235235],"iteration":74,"passed_time":0.04062118268,"remaining_time":0.5009945864},
{"learn":[1179.665151],"iteration":75,"passed_time":0.04110492944,"remaining_time":0.4997494053},
{"learn":[1176.362798],"iteration":76,"passed_time":0.04156534335,"remaining_time":0.4982443105},
{"learn":[1174.342911],"iteration":77,"passed_time":0.04212388161,"remaining_time":0.4979258826},
{"learn":[1172.566318],"iteration":78,"passed_time":0.04259587844,"remaining_time":0.4965924563},
{"learn":[1170.016304],"iteration":79,"passed_time":0.04303820848,"remaining_time":0.4949393975},
{"learn":[1168.068427],"iteration":80,"passed_time":0.04351716326,"remaining_time":0.4937317659},
{"learn":[1165.509581],"iteration":81,"passed_time":0.04394178542,"remaining_time":0.4919336465},
{"learn":[1162.815486],"iteration":82,"passed_time":0.0443914494,"remaining_time":0.4904452904},
{"learn":[1159.442429],"iteration":83,"passed_time":0.04485790528,"remaining_time":0.4891647766},
{"learn":[1156.455884],"iteration":84,"passed_time":0.04531081824,"remaining_time":0.4877576316},
{"learn":[1154.01067],"iteration":85,"passed_time":0.04580081496,"remaining_time":0.4867668008},
{"learn":[1151.673666],"iteration":86,"passed_time":0.0463008536,"remaining_time":0.485892866},
{"learn":[1148.985026],"iteration":87,"passed_time":0.04674085065,"remaining_time":0.4844051795},
{"learn":[1147.417282],"iteration":88,"passed_time":0.04717343075,"remaining_time":0.482865117},
{"learn":[1145.833583],"iteration":89,"passed_time":0.04753371934,"remaining_time":0.4806187178},
{"learn":[1143.289644],"iteration":90,"passed_time":0.0479722164,"remaining_time":0.4791949968},
{"learn":[1143.095429],"iteration":91,"passed_time":0.0482099648,"remaining_time":0.4758113918},
{"learn":[1140.05262],"iteration":92,"passed_time":0.04942566465,"remaining_time":0.4820330951},
{"learn":[1138.194983],"iteration":93,"passed_time":0.04982920395,"remaining_time":0.4802687104},
{"learn":[1136.973319],"iteration":94,"passed_time":0.05027228398,"remaining_time":0.4789096526},
{"learn":[1135.843695],"iteration":95,"passed_time":0.0505966148,"remaining_time":0.4764514561},
{"learn":[1134.742401],"iteration":96,"passed_time":0.05110711138,"remaining_time":0.4757703256},
{"learn":[1132.242621],"iteration":97,"passed_time":0.05146615098,"remaining_time":0.4736986549},
{"learn":[1130.223864],"iteration":98,"passed_time":0.05183344051,"remaining_time":0.4717366657},
{"learn":[1129.994363],"iteration":99,"passed_time":0.05212968853,"remaining_time":0.4691671967},
{"learn":[1128.402563],"iteration":100,"passed_time":0.05248481115,"remaining_time":0.4671667844},
{"learn":[1127.762454],"iteration":101,"passed_time":0.05302193255,"remaining_time":0.4668009355},
{"learn":[1126.145505],"iteration":102,"passed_time":0.05345476364,"remaining_time":0.4655235242},
{"learn":[1125.485885],"iteration":103,"passed_time":0.05399530202,"remaining_time":0.4651902943},
{"learn":[1124.164197],"iteration":104,"passed_time":0.0545644232,"remaining_time":0.4650967502},
{"learn":[1122.778258],"iteration":105,"passed_time":0.05532429311,"remaining_time":0.4666030004},
{"learn":[1121.064918],"iteration":106,"passed_time":0.05579524795,"remaining_time":0.4656556675},
{"learn":[1118.968248],"iteration":107,"passed_time":0.0562949946,"remaining_time":0.4649549554},
{"learn":[1116.4333],"iteration":108,"passed_time":0.05678995029,"remaining_time":0.4642187679},
{"learn":[1115.073056],"iteration":109,"passed_time":0.05732628069,"remaining_time":0.4638217256},
{"learn":[1113.420605],"iteration":110,"passed_time":0.05790769379,"remaining_time":0.4637832413},
{"learn":[1112.15146],"iteration":111,"passed_time":0.05849623185,"remaining_time":0.4637915525},
{"learn":[1111.18007],"iteration":112,"passed_time":0.0589811036,"remaining_time":0.4629755654},
{"learn":[1109.826887],"iteration":113,"passed_time":0.05944139251,"remaining_time":0.4619743313},
{"learn":[1107.763566],"iteration":114,"passed_time":0.05990380641,"remaining_time":0.460998858},
{"learn":[1106.327909],"iteration":115,"passed_time":0.06048105254,"remaining_time":0.4609073314},
{"learn":[1105.75436],"iteration":116,"passed_time":0.06084417511,"remaining_time":0.4591915096},
{"learn":[1104.112402],"iteration":117,"passed_time":0.06132517188,"remaining_time":0.4583796746},
{"learn":[1103.726357],"iteration":118,"passed_time":0.06177491887,"remaining_time":0.4573420464},
{"learn":[1102.535497],"iteration":119,"passed_time":0.06250478897,"remaining_time":0.4583684525},
{"learn":[1101.361324],"iteration":120,"passed_time":0.06326690886,"remaining_time":0.4596001065},
{"learn":[1099.540418],"iteration":121,"passed_time":0.06390832056,"remaining_time":0.4599303726},
{"learn":[1098.785518],"iteration":122,"passed_time":0.06442148312,"remaining_time":0.4593304122},
{"learn":[1097.48917],"iteration":123,"passed_time":0.06492956272,"remaining_time":0.4586959431},
{"learn":[1096.738446],"iteration":124,"passed_time":0.06543364234,"remaining_time":0.4580354964},
{"learn":[1096.108539],"iteration":125,"passed_time":0.06610313785,"remaining_time":0.4585249403},
{"learn":[1094.832948],"iteration":126,"passed_time":0.06666592608,"remaining_time":0.4582626257},
{"learn":[1093.930617],"iteration":127,"passed_time":0.06728408893,"remaining_time":0.4583728559},
{"learn":[1092.268909],"iteration":128,"passed_time":0.06790825175,"remaining_time":0.4585123044},
{"learn":[1091.353604],"iteration":129,"passed_time":0.06863303889,"remaining_time":0.4593134141},
{"learn":[1090.584505],"iteration":130,"passed_time":0.07001252964,"remaining_time":0.4644342615},
{"learn":[1090.004219],"iteration":131,"passed_time":0.07043398582,"remaining_time":0.4631568158},
{"learn":[1088.951386],"iteration":132,"passed_time":0.07139568737,"remaining_time":0.4654139921},
{"learn":[1087.396629],"iteration":133,"passed_time":0.07191143391,"remaining_time":0.464741058},
{"learn":[1086.000136],"iteration":134,"passed_time":0.0725248048,"remaining_time":0.4646959715},
{"learn":[1084.957326],"iteration":135,"passed_time":0.07322050814,"remaining_time":0.4651655811},
{"learn":[1083.459373],"iteration":136,"passed_time":0.0737774204,"remaining_time":0.4647438964},
{"learn":[1081.807667],"iteration":137,"passed_time":0.0742103755,"remaining_time":0.4635459687},
{"learn":[1081.57313],"iteration":138,"passed_time":0.07469045528,"remaining_time":0.4626509496},
{"learn":[1080.08663],"iteration":139,"passed_time":0.07505291085,"remaining_time":0.4610393095},
{"learn":[1079.984676],"iteration":140,"passed_time":0.07531995006,"remaining_time":0.4588640929},
{"learn":[1079.425844],"iteration":141,"passed_time":0.07589094623,"remaining_time":0.4585523371},
{"learn":[1078.206586],"iteration":142,"passed_time":0.0762992765,"remaining_time":0.4572620976},
{"learn":[1076.560274],"iteration":143,"passed_time":0.07660735743,"remaining_time":0.4553881803},
{"learn":[1075.496366],"iteration":144,"passed_time":0.07704189652,"remaining_time":0.4542815277},
{"learn":[1075.41013],"iteration":145,"passed_time":0.07718927053,"remaining_time":0.4515043632},
{"learn":[1074.868267],"iteration":146,"passed_time":0.07754639314,"remaining_time":0.4499800908},
{"learn":[1073.876651],"iteration":147,"passed_time":0.07793534853,"remaining_time":0.4486548442},
{"learn":[1072.898995],"iteration":148,"passed_time":0.07840526238,"remaining_time":0.4478045522},
{"learn":[1071.798894],"iteration":149,"passed_time":0.07900488336,"remaining_time":0.447694339},
{"learn":[1071.105274],"iteration":150,"passed_time":0.07925413169,"remaining_time":0.4456076676},
{"learn":[1069.810872],"iteration":151,"passed_time":0.07975337834,"remaining_time":0.4449399002},
{"learn":[1068.971038],"iteration":152,"passed_time":0.08012237587,"remaining_time":0.4435532834},
{"learn":[1068.263058],"iteration":153,"passed_time":0.08061153959,"remaining_time":0.4428400162},
{"learn":[1067.175132],"iteration":154,"passed_time":0.08109778633,"remaining_time":0.4421137384},
{"learn":[1066.502039],"iteration":155,"passed_time":0.08152715845,"remaining_time":0.4410828316},
{"learn":[1066.024869],"iteration":156,"passed_time":0.08194303066,"remaining_time":0.4399871009},
{"learn":[1064.796849],"iteration":157,"passed_time":0.08233440304,"remaining_time":0.4387694137},
{"learn":[1063.743314],"iteration":158,"passed_time":0.0828173998,"remaining_time":0.4380467499},
{"learn":[1062.945913],"iteration":159,"passed_time":0.08313810565,"remaining_time":0.4364750547},
{"learn":[1062.268779],"iteration":160,"passed_time":0.08358464466,"remaining_time":0.4355746389},
{"learn":[1061.225178],"iteration":161,"passed_time":0.08413439097,"remaining_time":0.4352137014},
{"learn":[1060.828112],"iteration":162,"passed_time":0.08461401276,"remaining_time":0.43449036},
{"learn":[1060.245328],"iteration":163,"passed_time":0.08501438507,"remaining_time":0.4333660117},
{"learn":[1059.614938],"iteration":164,"passed_time":0.08542146534,"remaining_time":0.4322843852},
{"learn":[1059.150831],"iteration":165,"passed_time":0.08585625443,"remaining_time":0.4313500975},
{"learn":[1058.811855],"iteration":166,"passed_time":0.08625220977,"remaining_time":0.4302280883},
{"learn":[1058.25998],"iteration":167,"passed_time":0.08657291562,"remaining_time":0.4287420583},
{"learn":[1056.943513],"iteration":168,"passed_time":0.08689966343,"remaining_time":0.4272995285},
{"learn":[1056.469452],"iteration":169,"passed_time":0.08720432839,"remaining_time":0.4257623092},
{"learn":[1054.832269],"iteration":170,"passed_time":0.08764020047,"remaining_time":0.4248755917},
{"learn":[1054.481285],"iteration":171,"passed_time":0.0880536977,"remaining_time":0.4238864052},
{"learn":[1052.980482],"iteration":172,"passed_time":0.08856790225,"remaining_time":0.4233852899},
{"learn":[1052.67967],"iteration":173,"passed_time":0.08904456605,"remaining_time":0.4227058136},
{"learn":[1051.92842],"iteration":174,"passed_time":0.08936210592,"remaining_time":0.4212784994},
{"learn":[1051.150782],"iteration":175,"passed_time":0.08977364517,"remaining_time":0.4203038842},
{"learn":[1050.220071],"iteration":176,"passed_time":0.09017922545,"remaining_time":0.419307924},
{"learn":[1049.39524],"iteration":177,"passed_time":0.09065493026,"remaining_time":0.4186424307},
{"learn":[1048.501738],"iteration":178,"passed_time":0.09165613255,"remaining_time":0.4203893007},
{"learn":[1047.970392],"iteration":179,"passed_time":0.09206400481,"remaining_time":0.4194026886},
{"learn":[1046.624118],"iteration":180,"passed_time":0.09251587678,"remaining_time":0.418621564},
{"learn":[1045.371336],"iteration":181,"passed_time":0.09297941567,"remaining_time":0.4178964946},
{"learn":[1045.117116],"iteration":182,"passed_time":0.09334145425,"remaining_time":0.4167211373},
{"learn":[1044.589525],"iteration":183,"passed_time":0.09377740932,"remaining_time":0.415882424},
{"learn":[1044.208797],"iteration":184,"passed_time":0.09414453186,"remaining_time":0.4147448296},
{"learn":[1043.559013],"iteration":185,"passed_time":0.09465106947,"remaining_time":0.4142256481},
{"learn":[1042.808906],"iteration":186,"passed_time":0.09509027452,"remaining_time":0.4134138673},
{"learn":[1042.76371],"iteration":187,"passed_time":0.09530773207,"remaining_time":0.4116482896},
{"learn":[1042.365726],"iteration":188,"passed_time":0.09576185402,"remaining_time":0.4109146223},
{"learn":[1041.945619],"iteration":189,"passed_time":0.09628893349,"remaining_time":0.410494927},
{"learn":[1040.857604],"iteration":190,"passed_time":0.09663264018,"remaining_time":0.4092974131},
{"learn":[1040.327174],"iteration":191,"passed_time":0.09708201217,"remaining_time":0.4085534679},
{"learn":[1039.646597],"iteration":192,"passed_time":0.09754509307,"remaining_time":0.4078698969},
{"learn":[1039.463762],"iteration":193,"passed_time":0.09782167421,"remaining_time":0.4064137599},
{"learn":[1038.209148],"iteration":194,"passed_time":0.09819779669,"remaining_time":0.4053806479},
{"learn":[1038.001971],"iteration":195,"passed_time":0.09873683508,"remaining_time":0.4050225276},
{"learn":[1037.965895],"iteration":196,"passed_time":0.09896841752,"remaining_time":0.4034093364},
{"learn":[1037.752878],"iteration":197,"passed_time":0.09938608172,"remaining_time":0.402563826},
{"learn":[1037.488343],"iteration":198,"passed_time":0.09982399479,"remaining_time":0.4018041197},
{"learn":[1037.116696],"iteration":199,"passed_time":0.1003458253,"remaining_time":0.4013833012},
{"learn":[1036.915358],"iteration":200,"passed_time":0.1006537392,"remaining_time":0.4001111325},
{"learn":[1036.077164],"iteration":201,"passed_time":0.1011135701,"remaining_time":0.3994486583},
{"learn":[1035.746893],"iteration":202,"passed_time":0.101431193,"remaining_time":0.3982298563},
{"learn":[1035.56442],"iteration":203,"passed_time":0.1017959406,"remaining_time":0.3972037681},
{"learn":[1034.904379],"iteration":204,"passed_time":0.102184438,"remaining_time":0.396276235},
{"learn":[1034.346919],"iteration":205,"passed_time":0.1027370173,"remaining_time":0.3959863675},
{"learn":[1034.015982],"iteration":206,"passed_time":0.1032052231,"remaining_time":0.395370734},
{"learn":[1033.141554],"iteration":207,"passed_time":0.103519555,"remaining_time":0.3941706133},
{"learn":[1031.489967],"iteration":208,"passed_time":0.1039897189,"remaining_time":0.3935687446},
{"learn":[1031.308478],"iteration":209,"passed_time":0.1044392988,"remaining_time":0.3928906957},
{"learn":[1029.908093],"iteration":210,"passed_time":0.1048263803,"remaining_time":0.3919811091},
{"learn":[1029.725789],"iteration":211,"passed_time":0.1051998777,"remaining_time":0.3910259607},
{"learn":[1029.513544],"iteration":212,"passed_time":0.1056240409,"remaining_time":0.3902634751},
{"learn":[1029.306816],"iteration":213,"passed_time":0.1060446211,"remaining_time":0.3894909915},
{"learn":[1029.046149],"iteration":214,"passed_time":0.106358827,"remaining_time":0.3883333915},
{"learn":[1028.225986],"iteration":215,"passed_time":0.1067642833,"remaining_time":0.3875148059},
{"learn":[1027.93232],"iteration":216,"passed_time":0.1071545306,"remaining_time":0.3866451497},
{"learn":[1026.39998],"iteration":217,"passed_time":0.1077201519,"remaining_time":0.3864089851},
{"learn":[1026.232992],"iteration":218,"passed_time":0.1081169412,"remaining_time":0.3855677218},
{"learn":[1026.072674],"iteration":219,"passed_time":0.1085725211,"remaining_time":0.3849389386},
{"learn":[1025.560236],"iteration":220,"passed_time":0.1089730185,"remaining_time":0.3841175628},
{"learn":[1025.259047],"iteration":221,"passed_time":0.1092963913,"remaining_time":0.3830296956},
{"learn":[1024.845364],"iteration":222,"passed_time":0.1096868887,"remaining_time":0.3821825672},
{"learn":[1024.534476],"iteration":223,"passed_time":0.1101664275,"remaining_time":0.3816479808},
{"learn":[1024.171298],"iteration":224,"passed_time":0.1106297993,"remaining_time":0.3810581978},
{"learn":[1023.083337],"iteration":225,"passed_time":0.1111839616,"remaining_time":0.3807804704},
{"learn":[1022.868887],"iteration":226,"passed_time":0.111578834,"remaining_time":0.3799578796},
{"learn":[1022.609299],"iteration":227,"passed_time":0.1119632894,"remaining_time":0.3791037694},
{"learn":[1022.4348],"iteration":228,"passed_time":0.112467077,"remaining_time":0.3786555301},
{"learn":[1021.818899],"iteration":229,"passed_time":0.1130350312,"remaining_time":0.3784216263},
{"learn":[1020.890936],"iteration":230,"passed_time":0.1134593204,"remaining_time":0.3777065687},
{"learn":[1020.569953],"iteration":231,"passed_time":0.1137617344,"remaining_time":0.3765905689},
{"learn":[1019.119756],"iteration":232,"passed_time":0.1143041057,"remaining_time":0.3762714553},
{"learn":[1018.91253],"iteration":233,"passed_time":0.1148193103,"remaining_time":0.3758615028},
{"learn":[1018.231112],"iteration":234,"passed_time":0.1152452234,"remaining_time":0.3751599826},
{"learn":[1017.253399],"iteration":235,"passed_time":0.115751803,"remaining_time":0.3747219386},
{"learn":[1016.917117],"iteration":236,"passed_time":0.1162261338,"remaining_time":0.3741794941},
{"learn":[1016.476018],"iteration":237,"passed_time":0.1166305471,"remaining_time":0.3734137685},
{"learn":[1015.468591],"iteration":238,"passed_time":0.1169865867,"remaining_time":0.3724970398},
{"learn":[1015.281338],"iteration":239,"passed_time":0.1173751681,"remaining_time":0.3716880324},
{"learn":[1015.158396],"iteration":240,"passed_time":0.1178924987,"remaining_time":0.3712879937},
{"learn":[1013.937869],"iteration":241,"passed_time":0.1182166635,"remaining_time":0.370281946},
{"learn":[1012.80134],"iteration":242,"passed_time":0.1187185351,"remaining_time":0.3698351074},
{"learn":[1012.667592],"iteration":243,"passed_time":0.1192127818,"remaining_time":0.3693641928},
{"learn":[1011.527412],"iteration":244,"passed_time":0.119635154,"remaining_time":0.3686715969},
{"learn":[1011.123466],"iteration":245,"passed_time":0.1201902753,"remaining_time":0.3683880794},
{"learn":[1010.040358],"iteration":246,"passed_time":0.120680438,"remaining_time":0.3679043311},
{"learn":[1009.701819],"iteration":247,"passed_time":0.1212260593,"remaining_time":0.367588696},
{"learn":[1009.444804],"iteration":248,"passed_time":0.1216789723,"remaining_time":0.3669915991},
{"learn":[1008.464231],"iteration":249,"passed_time":0.1223369679,"remaining_time":0.3670109036},
{"learn":[1008.20299],"iteration":250,"passed_time":0.1227981728,"remaining_time":0.3664375753},
{"learn":[1007.209095],"iteration":251,"passed_time":0.1231800032,"remaining_time":0.3656295333},
{"learn":[1007.091596],"iteration":252,"passed_time":0.1235615837,"remaining_time":0.3648241225},
{"learn":[1006.76884],"iteration":253,"passed_time":0.1239801228,"remaining_time":0.364130597},
{"learn":[1005.832099],"iteration":254,"passed_time":0.1244365778,"remaining_time":0.3635500018},
{"learn":[1005.716927],"iteration":255,"passed_time":0.1248050333,"remaining_time":0.3627146281},
{"learn":[1004.845997],"iteration":256,"passed_time":0.1251211142,"remaining_time":0.3617314702},
{"learn":[1004.129087],"iteration":257,"passed_time":0.125454403,"remaining_time":0.3608029729},
{"learn":[1003.963371],"iteration":258,"passed_time":0.1258296094,"remaining_time":0.3599989985},
{"learn":[1002.689484],"iteration":259,"passed_time":0.1262164819,"remaining_time":0.3592315253},
{"learn":[1002.527986],"iteration":260,"passed_time":0.126642604,"remaining_time":0.358578101},
{"learn":[1002.370326],"iteration":261,"passed_time":0.1270133095,"remaining_time":0.3577703146},
{"learn":[1001.752226],"iteration":262,"passed_time":0.1274502226,"remaining_time":0.3571513842},
{"learn":[1000.944152],"iteration":263,"passed_time":0.1279353853,"remaining_time":0.356668347},
{"learn":[1000.081947],"iteration":264,"passed_time":0.1283926323,"remaining_time":0.3561078669},
{"learn":[999.9314039],"iteration":265,"passed_time":0.1286805893,"remaining_time":0.3550810247},
{"learn":[999.7844358],"iteration":266,"passed_time":0.1291441272,"remaining_time":0.3545417425},
{"learn":[999.5984756],"iteration":267,"passed_time":0.1296064991,"remaining_time":0.3539998409},
{"learn":[999.3081235],"iteration":268,"passed_time":0.1302754946,"remaining_time":0.3540200245},
{"learn":[999.1678541],"iteration":269,"passed_time":0.1306607421,"remaining_time":0.3532679322},
{"learn":[998.0854231],"iteration":270,"passed_time":0.1310649894,"remaining_time":0.3525696577},
{"learn":[996.8438997],"iteration":271,"passed_time":0.1316467355,"remaining_time":0.3523486155},
{"learn":[995.9441988],"iteration":272,"passed_time":0.1320788156,"remaining_time":0.3517263696},
{"learn":[994.8078968],"iteration":273,"passed_time":0.1326328538,"remaining_time":0.3514286565},
{"learn":[993.8752206],"iteration":274,"passed_time":0.1329360608,"remaining_time":0.3504677967},
{"learn":[992.819213],"iteration":275,"passed_time":0.1334041827,"remaining_time":0.3499443053},
{"learn":[992.6824913],"iteration":276,"passed_time":0.1338123469,"remaining_time":0.3492647178},
{"learn":[992.3640639],"iteration":277,"passed_time":0.134245385,"remaining_time":0.3486516834},
{"learn":[991.481423],"iteration":278,"passed_time":0.1345760078,"remaining_time":0.3477752747},
{"learn":[991.3841743],"iteration":279,"passed_time":0.1349830891,"remaining_time":0.3470993719},
{"learn":[991.2524861],"iteration":280,"passed_time":0.1355167105,"remaining_time":0.3467491632},
{"learn":[991.1239216],"iteration":281,"passed_time":0.1361058316,"remaining_time":0.3465389612},
{"learn":[990.3794559],"iteration":282,"passed_time":0.1367323274,"remaining_time":0.3464207728},
{"learn":[989.0498385],"iteration":283,"passed_time":0.1372594908,"remaining_time":0.3460485755},
{"learn":[988.0799943],"iteration":284,"passed_time":0.138425442,"remaining_time":0.3472778633},
{"learn":[986.6186445],"iteration":285,"passed_time":0.1389444385,"remaining_time":0.3468752766},
{"learn":[985.6046794],"iteration":286,"passed_time":0.1394240193,"remaining_time":0.3463739574},
{"learn":[984.8248597],"iteration":287,"passed_time":0.1400894729,"remaining_time":0.3463323079},
{"learn":[984.7016882],"iteration":288,"passed_time":0.140512137,"remaining_time":0.3456890291},
{"learn":[984.1195043],"iteration":289,"passed_time":0.1409725509,"remaining_time":0.3451396937},
{"learn":[983.3685881],"iteration":290,"passed_time":0.1413995481,"remaining_time":0.3445095518},
{"learn":[982.5163561],"iteration":291,"passed_time":0.1419057527,"remaining_time":0.3440728524},
{"learn":[981.4201901],"iteration":292,"passed_time":0.1424041653,"remaining_time":0.3436168768},
{"learn":[980.2825087],"iteration":293,"passed_time":0.1427981627,"remaining_time":0.3429098737},
{"learn":[979.2465777],"iteration":294,"passed_time":0.143345534,"remaining_time":0.3425715305},
{"learn":[979.1264094],"iteration":295,"passed_time":0.1437689062,"remaining_time":0.341936858},
{"learn":[978.3369426],"iteration":296,"passed_time":0.1441346957,"remaining_time":0.3411673101},
{"learn":[977.5165819],"iteration":297,"passed_time":0.1446186085,"remaining_time":0.3406787354},
{"learn":[977.4300322],"iteration":298,"passed_time":0.1449797311,"remaining_time":0.3399023126},
{"learn":[976.3741464],"iteration":299,"passed_time":0.145295354,"remaining_time":0.3390224926},
{"learn":[975.6514041],"iteration":300,"passed_time":0.145738476,"remaining_time":0.3384425073},
{"learn":[975.0801288],"iteration":301,"passed_time":0.1461265984,"remaining_time":0.3377363102},
{"learn":[973.9057578],"iteration":302,"passed_time":0.1464897629,"remaining_time":0.3369748012},
{"learn":[973.7549889],"iteration":303,"passed_time":0.1470368013,"remaining_time":0.3366368871},
{"learn":[973.6701217],"iteration":304,"passed_time":0.1475138821,"remaining_time":0.3361381903},
{"learn":[972.5913894],"iteration":305,"passed_time":0.1480496705,"remaining_time":0.3357727821},
{"learn":[972.0662198],"iteration":306,"passed_time":0.1485793329,"remaining_time":0.3353924356},
{"learn":[971.3033543],"iteration":307,"passed_time":0.1489182477,"remaining_time":0.3345825564},
{"learn":[971.2037877],"iteration":308,"passed_time":0.1492699113,"remaining_time":0.3338042353},
{"learn":[970.1877987],"iteration":309,"passed_time":0.1498839072,"remaining_time":0.3336125676},
{"learn":[969.500992],"iteration":310,"passed_time":0.1503105713,"remaining_time":0.3330031629},
{"learn":[969.3761183],"iteration":311,"passed_time":0.1507193186,"remaining_time":0.3323554205},
{"learn":[968.7334509],"iteration":312,"passed_time":0.1510374835,"remaining_time":0.331510387},
{"learn":[968.6253063],"iteration":313,"passed_time":0.1513256905,"remaining_time":0.3306032602},
{"learn":[967.9326681],"iteration":314,"passed_time":0.1518596449,"remaining_time":0.330234466},
{"learn":[967.0543294],"iteration":315,"passed_time":0.1522372254,"remaining_time":0.3295261462},
{"learn":[966.4720636],"iteration":316,"passed_time":0.1526485557,"remaining_time":0.3288926294},
{"learn":[965.5505401],"iteration":317,"passed_time":0.1530963447,"remaining_time":0.3283387014},
{"learn":[964.5819295],"iteration":318,"passed_time":0.1534236345,"remaining_time":0.3275281977},
{"learn":[963.5741464],"iteration":319,"passed_time":0.1538740484,"remaining_time":0.3269823529},
{"learn":[963.4703117],"iteration":320,"passed_time":0.1543143795,"remaining_time":0.3264157747},
{"learn":[962.3959064],"iteration":321,"passed_time":0.1546667521,"remaining_time":0.3256647762},
{"learn":[961.4554388],"iteration":322,"passed_time":0.1551772897,"remaining_time":0.3252477558},
{"learn":[961.1430461],"iteration":323,"passed_time":0.1563388649,"remaining_time":0.3261884959},
{"learn":[959.7363948],"iteration":324,"passed_time":0.1567147374,"remaining_time":0.3254844546},
{"learn":[959.1523094],"iteration":325,"passed_time":0.1571345676,"remaining_time":0.3248733084},
{"learn":[959.0243003],"iteration":326,"passed_time":0.157517606,"remaining_time":0.3241876112},
{"learn":[958.2439289],"iteration":327,"passed_time":0.1579568941,"remaining_time":0.3236190025},
{"learn":[958.1740791],"iteration":328,"passed_time":0.1584577657,"remaining_time":0.3231767805},
{"learn":[958.0927492],"iteration":329,"passed_time":0.1588450541,"remaining_time":0.3225035947},
{"learn":[957.0175169],"iteration":330,"passed_time":0.1593518007,"remaining_time":0.3220735791},
{"learn":[956.4762583],"iteration":331,"passed_time":0.159911588,"remaining_time":0.3217498216},
{"learn":[955.5518416],"iteration":332,"passed_time":0.16050275,"remaining_time":0.3214874902},
{"learn":[955.4830638],"iteration":333,"passed_time":0.160952288,"remaining_time":0.3209407898},
{"learn":[955.1303562],"iteration":334,"passed_time":0.1614643676,"remaining_time":0.3205188192},
{"learn":[954.4228742],"iteration":335,"passed_time":0.1619839051,"remaining_time":0.3201110505},
{"learn":[953.9286891],"iteration":336,"passed_time":0.1624961936,"remaining_time":0.3196883572},
{"learn":[953.8354632],"iteration":337,"passed_time":0.1628713581,"remaining_time":0.3189965653},
{"learn":[952.5750936],"iteration":338,"passed_time":0.1631667311,"remaining_time":0.3181510598},
{"learn":[952.069721],"iteration":339,"passed_time":0.1635735204,"remaining_time":0.317525069},
{"learn":[951.5580313],"iteration":340,"passed_time":0.1640621421,"remaining_time":0.3170585093},
{"learn":[950.3900565],"iteration":341,"passed_time":0.1643984319,"remaining_time":0.3162987374},
{"learn":[950.3117499],"iteration":342,"passed_time":0.1647607635,"remaining_time":0.3155913166},
{"learn":[950.2351432],"iteration":343,"passed_time":0.1651636358,"remaining_time":0.3149632124},
{"learn":[949.7869881],"iteration":344,"passed_time":0.1655145914,"remaining_time":0.3142378475},
{"learn":[949.1289185],"iteration":345,"passed_time":0.16602613,"remaining_time":0.3138181763},
{"learn":[948.4404287],"iteration":346,"passed_time":0.1663319189,"remaining_time":0.3130107869},
{"learn":[947.2665422],"iteration":347,"passed_time":0.1666732506,"remaining_time":0.3122728719},
{"learn":[946.6273579],"iteration":348,"passed_time":0.1672533297,"remaining_time":0.3119825721},
{"learn":[945.9649297],"iteration":349,"passed_time":0.1677232016,"remaining_time":0.3114859458},
{"learn":[945.9090979],"iteration":350,"passed_time":0.1681700316,"remaining_time":0.3109468676},
{"learn":[945.4251093],"iteration":351,"passed_time":0.1686564033,"remaining_time":0.3104811062},
{"learn":[944.4213244],"iteration":352,"passed_time":0.1690637336,"remaining_time":0.3098703559},
{"learn":[944.3500405],"iteration":353,"passed_time":0.1694813968,"remaining_time":0.3092796111},
{"learn":[943.5586165],"iteration":354,"passed_time":0.1698202285,"remaining_time":0.3085466124},
{"learn":[943.477781],"iteration":355,"passed_time":0.1701009347,"remaining_time":0.3077106796},
{"learn":[943.3843765],"iteration":356,"passed_time":0.1704815991,"remaining_time":0.3070578942},
{"learn":[942.6815228],"iteration":357,"passed_time":0.171094803,"remaining_time":0.3068236411},
{"learn":[941.8718165],"iteration":358,"passed_time":0.1716768401,"remaining_time":0.3065316281},
{"learn":[941.2767906],"iteration":359,"passed_time":0.1720206288,"remaining_time":0.3058144512},
{"learn":[941.1994805],"iteration":360,"passed_time":0.1723771264,"remaining_time":0.3051218387},
{"learn":[940.1083289],"iteration":361,"passed_time":0.1727432069,"remaining_time":0.3044479725},
{"learn":[939.641626],"iteration":362,"passed_time":0.1731627451,"remaining_time":0.3038696106},
{"learn":[939.0561418],"iteration":363,"passed_time":0.1736823666,"remaining_time":0.3034669923},
{"learn":[938.5820894],"iteration":364,"passed_time":0.174080405,"remaining_time":0.3028522114},
{"learn":[938.1206465],"iteration":365,"passed_time":0.1744810273,"remaining_time":0.302243091},
{"learn":[937.3254278],"iteration":366,"passed_time":0.1750026488,"remaining_time":0.3018438057},
{"learn":[936.2916764],"iteration":367,"passed_time":0.1753382715,"remaining_time":0.3011244229},
{"learn":[935.2813601],"iteration":368,"passed_time":0.1759127257,"remaining_time":0.3008155282},
{"learn":[935.2175528],"iteration":369,"passed_time":0.1761804739,"remaining_time":0.2999829691},
{"learn":[934.5982487],"iteration":370,"passed_time":0.1765322635,"remaining_time":0.2992959401},
{"learn":[933.998002],"iteration":371,"passed_time":0.1768553024,"remaining_time":0.2985621771},
{"learn":[933.3162318],"iteration":372,"passed_time":0.1772714246,"remaining_time":0.2979870864},
{"learn":[932.5815096],"iteration":373,"passed_time":0.1776039224,"remaining_time":0.2972728754},
{"learn":[932.1599136],"iteration":374,"passed_time":0.1779859198,"remaining_time":0.2966431997},
{"learn":[931.7093101],"iteration":375,"passed_time":0.178405542,"remaining_time":0.2960772824},
{"learn":[931.6501652],"iteration":376,"passed_time":0.1788383721,"remaining_time":0.2955339677},
{"learn":[930.8888163],"iteration":377,"passed_time":0.1792466603,"remaining_time":0.2949508538},
{"learn":[930.3732313],"iteration":378,"passed_time":0.1797544489,"remaining_time":0.294531696},
{"learn":[929.4400293],"iteration":379,"passed_time":0.1804997349,"remaining_time":0.2944995675},
{"learn":[929.3749911],"iteration":380,"passed_time":0.1810622732,"remaining_time":0.2941667903},
{"learn":[928.4801416],"iteration":381,"passed_time":0.1814386047,"remaining_time":0.2935315646},
{"learn":[928.4236677],"iteration":382,"passed_time":0.1820453506,"remaining_time":0.2932688807},
{"learn":[927.9597556],"iteration":383,"passed_time":0.182432931,"remaining_time":0.2926528268},
{"learn":[927.1787364],"iteration":384,"passed_time":0.1831278433,"remaining_time":0.2925288926},
{"learn":[926.3887709],"iteration":385,"passed_time":0.1834870909,"remaining_time":0.2918680669},
{"learn":[925.5155031],"iteration":386,"passed_time":0.1839910465,"remaining_time":0.2914380143},
{"learn":[925.4172767],"iteration":387,"passed_time":0.184365502,"remaining_time":0.2908033176},
{"learn":[924.9867482],"iteration":388,"passed_time":0.1854770356,"remaining_time":0.2913276831},
{"learn":[924.1986817],"iteration":389,"passed_time":0.1859510324,"remaining_time":0.2908464866},
{"learn":[923.7718611],"iteration":390,"passed_time":0.1863374878,"remaining_time":0.2902289772},
{"learn":[922.8747635],"iteration":391,"passed_time":0.1868633593,"remaining_time":0.2898288838},
{"learn":[922.4017374],"iteration":392,"passed_time":0.1874381054,"remaining_time":0.2895036387},
{"learn":[922.3381521],"iteration":393,"passed_time":0.1879711019,"remaining_time":0.289112913},
{"learn":[921.6444918],"iteration":394,"passed_time":0.1885718898,"remaining_time":0.2888252996},
{"learn":[921.1935387],"iteration":395,"passed_time":0.1890655955,"remaining_time":0.288372777},
{"learn":[920.5108309],"iteration":396,"passed_time":0.1901041306,"remaining_time":0.2887475837},
{"learn":[919.4927005],"iteration":397,"passed_time":0.1906763357,"remaining_time":0.2884099349},
{"learn":[918.7651292],"iteration":398,"passed_time":0.1910102505,"remaining_time":0.2877121818},
{"learn":[918.2386282],"iteration":399,"passed_time":0.1915219131,"remaining_time":0.2872828696},
{"learn":[918.1820943],"iteration":400,"passed_time":0.1919134514,"remaining_time":0.2866737092},
{"learn":[917.8634359],"iteration":401,"passed_time":0.1922224074,"remaining_time":0.2859427851},
{"learn":[917.4191598],"iteration":402,"passed_time":0.1927082791,"remaining_time":0.2854760363},
{"learn":[915.8856856],"iteration":403,"passed_time":0.1931496091,"remaining_time":0.2849434828},
{"learn":[915.4701588],"iteration":404,"passed_time":0.1937775629,"remaining_time":0.2846855554},
{"learn":[914.7444772],"iteration":405,"passed_time":0.1942316849,"remaining_time":0.2841714799},
{"learn":[914.6664866],"iteration":406,"passed_time":0.1948272229,"remaining_time":0.2838637425},
{"learn":[914.2558989],"iteration":407,"passed_time":0.195405677,"remaining_time":0.2835298059},
{"learn":[913.8446686],"iteration":408,"passed_time":0.1958711739,"remaining_time":0.2830314518},
{"learn":[913.3695321],"iteration":409,"passed_time":0.1962677132,"remaining_time":0.2824340264},
{"learn":[912.6783206],"iteration":410,"passed_time":0.1967019603,"remaining_time":0.2818916171},
{"learn":[912.125002],"iteration":411,"passed_time":0.1972692905,"remaining_time":0.2815396671},
{"learn":[911.5405546],"iteration":412,"passed_time":0.19765058,"remaining_time":0.2809222529},
{"learn":[910.6478483],"iteration":413,"passed_time":0.1981937843,"remaining_time":0.2805351633},
{"learn":[910.087048],"iteration":414,"passed_time":0.1986480313,"remaining_time":0.2800219236},
{"learn":[910.029343],"iteration":415,"passed_time":0.1990151948,"remaining_time":0.2793867158},
{"learn":[909.5829454],"iteration":416,"passed_time":0.1993629005,"remaining_time":0.2787255899},
{"learn":[908.9411229],"iteration":417,"passed_time":0.1997781477,"remaining_time":0.2781600047},
{"learn":[908.388598],"iteration":418,"passed_time":0.2002998532,"remaining_time":0.2777427559},
{"learn":[908.2988322],"iteration":419,"passed_time":0.200635226,"remaining_time":0.277067693},
{"learn":[908.2410622],"iteration":420,"passed_time":0.2010023065,"remaining_time":0.2764378515},
{"learn":[907.5080034],"iteration":421,"passed_time":0.2015501358,"remaining_time":0.2760568211},
{"learn":[906.6979331],"iteration":422,"passed_time":0.2021070071,"remaining_time":0.2756873359},
{"learn":[906.1937773],"iteration":423,"passed_time":0.2024744216,"remaining_time":0.2750595916},
{"learn":[905.577991],"iteration":424,"passed_time":0.2029672933,"remaining_time":0.2746028086},
{"learn":[904.65595],"iteration":425,"passed_time":0.2033364159,"remaining_time":0.2739791143},
{"learn":[904.6003855],"iteration":426,"passed_time":0.203754913,"remaining_time":0.2734228693},
{"learn":[903.7172908],"iteration":427,"passed_time":0.2044854501,"remaining_time":0.2732842932},
{"learn":[903.6664812],"iteration":428,"passed_time":0.2048808645,"remaining_time":0.2726969082},
{"learn":[902.603235],"iteration":429,"passed_time":0.2053615283,"remaining_time":0.2722234212},
{"learn":[901.8818322],"iteration":430,"passed_time":0.2059578993,"remaining_time":0.2719026559},
{"learn":[901.2224834],"iteration":431,"passed_time":0.2064753548,"remaining_time":0.2714768554},
{"learn":[900.8744149],"iteration":432,"passed_time":0.2068164775,"remaining_time":0.2708197292},
{"learn":[900.4180311],"iteration":433,"passed_time":0.2072143079,"remaining_time":0.2702380144},
{"learn":[899.7967696],"iteration":434,"passed_time":0.2075605145,"remaining_time":0.2695900936},
{"learn":[899.0274016],"iteration":435,"passed_time":0.2079468449,"remaining_time":0.26899546},
{"learn":[898.975359],"iteration":436,"passed_time":0.208387425,"remaining_time":0.2684716711},
{"learn":[898.5478275],"iteration":437,"passed_time":0.208832505,"remaining_time":0.2679540361},
{"learn":[897.9975905],"iteration":438,"passed_time":0.2093334176,"remaining_time":0.2675080804},
{"learn":[897.3687331],"iteration":439,"passed_time":0.2096770813,"remaining_time":0.2668617399},
{"learn":[896.7626608],"iteration":440,"passed_time":0.2100905376,"remaining_time":0.2663052392},
{"learn":[896.2759297],"iteration":441,"passed_time":0.2105510345,"remaining_time":0.265808772},
{"learn":[895.8727764],"iteration":442,"passed_time":0.2110143644,"remaining_time":0.2653160293},
{"learn":[895.3353749],"iteration":443,"passed_time":0.2114024028,"remaining_time":0.264729135},
{"learn":[894.8922662],"iteration":444,"passed_time":0.2117153597,"remaining_time":0.2640494935},
{"learn":[894.4361346],"iteration":445,"passed_time":0.2120103167,"remaining_time":0.2633491378},
{"learn":[894.388289],"iteration":446,"passed_time":0.2125189803,"remaining_time":0.2629149801},
{"learn":[893.7878153],"iteration":447,"passed_time":0.2129421445,"remaining_time":0.2623751423},
{"learn":[893.7393178],"iteration":448,"passed_time":0.2133678916,"remaining_time":0.2618389939},
{"learn":[893.6618209],"iteration":449,"passed_time":0.2138540133,"remaining_time":0.2613771274},
{"learn":[893.6193299],"iteration":450,"passed_time":0.2142783855,"remaining_time":0.2608399859},
{"learn":[892.8291473],"iteration":451,"passed_time":0.2148335068,"remaining_time":0.2604618622},
{"learn":[892.2692834],"iteration":452,"passed_time":0.2152655459,"remaining_time":0.2599343346},
{"learn":[892.1971034],"iteration":453,"passed_time":0.2157474586,"remaining_time":0.259467208},
{"learn":[891.4463914],"iteration":454,"passed_time":0.2161649148,"remaining_time":0.2589228101},
{"learn":[890.8971902],"iteration":455,"passed_time":0.2167831607,"remaining_time":0.2586185075},
{"learn":[890.85037],"iteration":456,"passed_time":0.2172000739,"remaining_time":0.2580736108},
{"learn":[889.9839803],"iteration":457,"passed_time":0.217641321,"remaining_time":0.2575580698},
{"learn":[889.4917061],"iteration":458,"passed_time":0.2180169014,"remaining_time":0.2569654546},
{"learn":[888.9360457],"iteration":459,"passed_time":0.2184891063,"remaining_time":0.2564872117},
{"learn":[888.5109483],"iteration":460,"passed_time":0.218977353,"remaining_time":0.2560277511},
{"learn":[888.4664415],"iteration":461,"passed_time":0.2194495588,"remaining_time":0.2555494863},
{"learn":[887.9746833],"iteration":462,"passed_time":0.2200129301,"remaining_time":0.2551769837},
{"learn":[887.9342803],"iteration":463,"passed_time":0.2203890525,"remaining_time":0.2545873538},
{"learn":[887.896189],"iteration":464,"passed_time":0.2208532164,"remaining_time":0.2540999372},
{"learn":[887.2405313],"iteration":465,"passed_time":0.2213031304,"remaining_time":0.2535962911},
{"learn":[886.7652732],"iteration":466,"passed_time":0.221661378,"remaining_time":0.2529882537},
{"learn":[886.2838761],"iteration":467,"passed_time":0.221961126,"remaining_time":0.2523147842},
{"learn":[885.7648487],"iteration":468,"passed_time":0.2224402478,"remaining_time":0.2518459948},
{"learn":[885.632831],"iteration":469,"passed_time":0.2229640353,"remaining_time":0.2514275291},
{"learn":[884.9735854],"iteration":470,"passed_time":0.2234799898,"remaining_time":0.2509998187},
{"learn":[884.4283454],"iteration":471,"passed_time":0.2239961114,"remaining_time":0.2505719212},
{"learn":[884.0511815],"iteration":472,"passed_time":0.2243198592,"remaining_time":0.2499293146},
{"learn":[883.5366335],"iteration":473,"passed_time":0.2250208955,"remaining_time":0.2497067321},
{"learn":[883.4664384],"iteration":474,"passed_time":0.2256468083,"remaining_time":0.2493991039},
{"learn":[883.4233873],"iteration":475,"passed_time":0.2259410973,"remaining_time":0.2487250735},
{"learn":[883.3978692],"iteration":476,"passed_time":0.226293095,"remaining_time":0.2481159091},
{"learn":[882.6868413],"iteration":477,"passed_time":0.2267521749,"remaining_time":0.24762476},
{"learn":[882.3058892],"iteration":478,"passed_time":0.2272252557,"remaining_time":0.2471489733},
{"learn":[881.4135804],"iteration":479,"passed_time":0.2277118774,"remaining_time":0.2466878672},
{"learn":[881.3723373],"iteration":480,"passed_time":0.228082875,"remaining_time":0.2461018963},
{"learn":[881.3321746],"iteration":481,"passed_time":0.2286229133,"remaining_time":0.2456984836},
{"learn":[880.4585627],"iteration":482,"passed_time":0.2290298686,"remaining_time":0.245152054},
{"learn":[879.8281037],"iteration":483,"passed_time":0.2293585754,"remaining_time":0.2445227787},
{"learn":[879.183418],"iteration":484,"passed_time":0.2297670727,"remaining_time":0.2439794689},
{"learn":[878.5523954],"iteration":485,"passed_time":0.2301009044,"remaining_time":0.2433577467},
{"learn":[878.5141765],"iteration":486,"passed_time":0.2304156933,"remaining_time":0.2427171472},
{"learn":[877.8525915],"iteration":487,"passed_time":0.2309204819,"remaining_time":0.2422772269},
{"learn":[876.9206027],"iteration":488,"passed_time":0.2312583547,"remaining_time":0.241662616},
{"learn":[876.2984818],"iteration":489,"passed_time":0.231806809,"remaining_time":0.2412683114},
{"learn":[875.6213472],"iteration":490,"passed_time":0.232249181,"remaining_time":0.2407634076},
{"learn":[875.4432762],"iteration":491,"passed_time":0.2328910097,"remaining_time":0.2404647011},
{"learn":[874.8668781],"iteration":492,"passed_time":0.2333607146,"remaining_time":0.2399875908},
{"learn":[874.2092133],"iteration":493,"passed_time":0.234039002,"remaining_time":0.23972416},
{"learn":[874.1762177],"iteration":494,"passed_time":0.2345110399,"remaining_time":0.2392486366},
{"learn":[874.0637575],"iteration":495,"passed_time":0.235092077,"remaining_time":0.2388838847},
{"learn":[873.9976179],"iteration":496,"passed_time":0.2355463239,"remaining_time":0.2383899415},
{"learn":[873.9603508],"iteration":497,"passed_time":0.2359944039,"remaining_time":0.2378899413},
{"learn":[873.9269941],"iteration":498,"passed_time":0.236428609,"remaining_time":0.2373762187},
{"learn":[872.8743591],"iteration":499,"passed_time":0.2370162301,"remaining_time":0.2370162301},
{"learn":[872.5383293],"iteration":500,"passed_time":0.2375736853,"remaining_time":0.2366252874},
{"learn":[872.1985989],"iteration":501,"passed_time":0.2380860149,"remaining_time":0.2361889152},
{"learn":[871.6057169],"iteration":502,"passed_time":0.2386835109,"remaining_time":0.2358363915},
{"learn":[870.9417047],"iteration":503,"passed_time":0.2391265079,"remaining_time":0.2353308491},
{"learn":[870.4960773],"iteration":504,"passed_time":0.2395786299,"remaining_time":0.2348344986},
{"learn":[869.9588191],"iteration":505,"passed_time":0.2399568774,"remaining_time":0.2342662004},
{"learn":[869.6278862],"iteration":506,"passed_time":0.2405927071,"remaining_time":0.2339491215},
{"learn":[869.2222733],"iteration":507,"passed_time":0.2409547887,"remaining_time":0.2333656615},
{"learn":[869.1626968],"iteration":508,"passed_time":0.2414553693,"remaining_time":0.2329166726},
{"learn":[868.7896361],"iteration":509,"passed_time":0.2417624922,"remaining_time":0.2322816102},
{"learn":[868.7319991],"iteration":510,"passed_time":0.2420662402,"remaining_time":0.2316446017},
{"learn":[868.1287182],"iteration":511,"passed_time":0.242551362,"remaining_time":0.2311817669},
{"learn":[867.403758],"iteration":512,"passed_time":0.242996609,"remaining_time":0.2306809914},
{"learn":[867.3479491],"iteration":513,"passed_time":0.2433292317,"remaining_time":0.2300739429},
{"learn":[867.1238582],"iteration":514,"passed_time":0.2438708941,"remaining_time":0.2296648226},
{"learn":[866.3731249],"iteration":515,"passed_time":0.2444654321,"remaining_time":0.2293047852},
{"learn":[866.2919215],"iteration":516,"passed_time":0.2450485112,"remaining_time":0.2289331352},
{"learn":[865.9228086],"iteration":517,"passed_time":0.2454147168,"remaining_time":0.2283588677},
{"learn":[865.352],"iteration":518,"passed_time":0.2457735064,"remaining_time":0.227778529},
{"learn":[864.996357],"iteration":519,"passed_time":0.2462051285,"remaining_time":0.2272662724},
{"learn":[864.9419766],"iteration":520,"passed_time":0.2465447512,"remaining_time":0.2266697425},
{"learn":[864.179863],"iteration":521,"passed_time":0.2469342906,"remaining_time":0.2261199059},
{"learn":[863.6465483],"iteration":522,"passed_time":0.247472787,"remaining_time":0.225706538},
{"learn":[863.3460674],"iteration":523,"passed_time":0.2477942848,"remaining_time":0.2250955717},
{"learn":[862.9933655],"iteration":524,"passed_time":0.2482311979,"remaining_time":0.2245901314},
{"learn":[862.5557884],"iteration":525,"passed_time":0.2486329452,"remaining_time":0.2240532624},
{"learn":[862.15472],"iteration":526,"passed_time":0.2490741512,"remaining_time":0.2235523217},
{"learn":[861.6285616],"iteration":527,"passed_time":0.2494306078,"remaining_time":0.2229758464},
{"learn":[861.3580607],"iteration":528,"passed_time":0.2498281052,"remaining_time":0.2224367439},
{"learn":[861.307068],"iteration":529,"passed_time":0.2502769352,"remaining_time":0.2219436972},
{"learn":[860.5038496],"iteration":530,"passed_time":0.2509638476,"remaining_time":0.2216611008},
{"learn":[859.9037157],"iteration":531,"passed_time":0.2514255535,"remaining_time":0.2211788703},
{"learn":[859.3975775],"iteration":532,"passed_time":0.2519685088,"remaining_time":0.2207679055},
{"learn":[858.4425491],"iteration":533,"passed_time":0.2523514653,"remaining_time":0.2202168217},
{"learn":[858.0011505],"iteration":534,"passed_time":0.2527399207,"remaining_time":0.219671146},
{"learn":[857.3468134],"iteration":535,"passed_time":0.2532350833,"remaining_time":0.2192184303},
{"learn":[856.8976101],"iteration":536,"passed_time":0.2543074511,"remaining_time":0.2192632214},
{"learn":[856.3343574],"iteration":537,"passed_time":0.2548244887,"remaining_time":0.2188269773},
{"learn":[855.8266501],"iteration":538,"passed_time":0.2552667357,"remaining_time":0.218326466},
{"learn":[855.3665629],"iteration":539,"passed_time":0.2557166487,"remaining_time":0.2178327007},
{"learn":[854.905719],"iteration":540,"passed_time":0.256125521,"remaining_time":0.2173042775},
{"learn":[854.8573481],"iteration":541,"passed_time":0.2564840606,"remaining_time":0.2167337633},
{"learn":[854.4350569],"iteration":542,"passed_time":0.2569920161,"remaining_time":0.2162897815},
{"learn":[854.3276675],"iteration":543,"passed_time":0.2573284299,"remaining_time":0.2157017721},
{"learn":[854.029492],"iteration":544,"passed_time":0.2577770929,"remaining_time":0.2152083986},
{"learn":[853.6815158],"iteration":545,"passed_time":0.2581609653,"remaining_time":0.2146613155},
{"learn":[853.3021867],"iteration":546,"passed_time":0.2586842538,"remaining_time":0.214230287},
{"learn":[852.926125],"iteration":547,"passed_time":0.2591981674,"remaining_time":0.2137911891},
{"learn":[852.8805183],"iteration":548,"passed_time":0.2594871654,"remaining_time":0.2131670521},
{"learn":[852.5066224],"iteration":549,"passed_time":0.2599384534,"remaining_time":0.2126769164},
{"learn":[852.4707239],"iteration":550,"passed_time":0.2604085342,"remaining_time":0.2122022357},
{"learn":[852.0253981],"iteration":551,"passed_time":0.2608718221,"remaining_time":0.2117220585},
{"learn":[851.4706475],"iteration":552,"passed_time":0.2613605689,"remaining_time":0.2112625213},
{"learn":[851.1917175],"iteration":553,"passed_time":0.2618320237,"remaining_time":0.2107889577},
{"learn":[850.6917349],"iteration":554,"passed_time":0.2624934783,"remaining_time":0.2104677438},
{"learn":[850.2853342],"iteration":555,"passed_time":0.2631165151,"remaining_time":0.2101146272},
{"learn":[849.8456636],"iteration":556,"passed_time":0.2636696784,"remaining_time":0.2097049686},
{"learn":[849.2710766],"iteration":557,"passed_time":0.2644245483,"remaining_time":0.2094545705},
{"learn":[848.8568451],"iteration":558,"passed_time":0.2654264576,"remaining_time":0.209397259},
{"learn":[848.7666197],"iteration":559,"passed_time":0.2658370379,"remaining_time":0.2088719583},
{"learn":[848.2224711],"iteration":560,"passed_time":0.2663285346,"remaining_time":0.2084103862},
{"learn":[847.8597635],"iteration":561,"passed_time":0.266860322,"remaining_time":0.2079801086},
{"learn":[847.5661768],"iteration":562,"passed_time":0.2671953617,"remaining_time":0.207396755},
{"learn":[847.2994936],"iteration":563,"passed_time":0.2675487344,"remaining_time":0.2068284542},
{"learn":[846.5900716],"iteration":564,"passed_time":0.2679328568,"remaining_time":0.2062845889},
{"learn":[846.5084069],"iteration":565,"passed_time":0.2683061043,"remaining_time":0.2057329492},
{"learn":[845.9781176],"iteration":566,"passed_time":0.2687324764,"remaining_time":0.2052225085},
{"learn":[845.9508879],"iteration":567,"passed_time":0.2690045576,"remaining_time":0.2045950157},
{"learn":[845.2885693],"iteration":568,"passed_time":0.2693126386,"remaining_time":0.2039960408},
{"learn":[844.7280133],"iteration":569,"passed_time":0.2696698032,"remaining_time":0.2034351147},
{"learn":[844.4182565],"iteration":570,"passed_time":0.2700772164,"remaining_time":0.2029126547},
{"learn":[843.8509958],"iteration":571,"passed_time":0.2704760888,"remaining_time":0.2023842063},
{"learn":[843.4678871],"iteration":572,"passed_time":0.2708296704,"remaining_time":0.2018224594},
{"learn":[843.3901283],"iteration":573,"passed_time":0.2712934593,"remaining_time":0.2013432294},
{"learn":[843.3651654],"iteration":574,"passed_time":0.2717300393,"remaining_time":0.2008439421},
{"learn":[843.3261422],"iteration":575,"passed_time":0.2721050788,"remaining_time":0.2002995719},
{"learn":[842.771839],"iteration":576,"passed_time":0.2726549081,"remaining_time":0.1998839275},
{"learn":[842.4113411],"iteration":577,"passed_time":0.27311703,"remaining_time":0.1994037832},
{"learn":[842.1262557],"iteration":578,"passed_time":0.2736486935,"remaining_time":0.1989742659},
{"learn":[842.0976039],"iteration":579,"passed_time":0.2741102744,"remaining_time":0.198493647},
{"learn":[841.5016503],"iteration":580,"passed_time":0.2744206883,"remaining_time":0.1979040764},
{"learn":[840.9824334],"iteration":581,"passed_time":0.2748865602,"remaining_time":0.1974271171},
{"learn":[840.5378279],"iteration":582,"passed_time":0.2752651406,"remaining_time":0.1968877593},
{"learn":[840.0276344],"iteration":583,"passed_time":0.275804553,"remaining_time":0.1964635172},
{"learn":[839.9532507],"iteration":584,"passed_time":0.2761731346,"remaining_time":0.1959176937},
{"learn":[839.4271973],"iteration":585,"passed_time":0.2765051323,"remaining_time":0.1953466293},
{"learn":[839.2977742],"iteration":586,"passed_time":0.276856546,"remaining_time":0.19479004},
{"learn":[839.275093],"iteration":587,"passed_time":0.2772543353,"remaining_time":0.1942666431},
{"learn":[838.8770476],"iteration":588,"passed_time":0.2776166249,"remaining_time":0.1937189012},
{"learn":[838.5230742],"iteration":589,"passed_time":0.2780867467,"remaining_time":0.1932467223},
{"learn":[837.5871643],"iteration":590,"passed_time":0.2785941183,"remaining_time":0.1928003289},
{"learn":[837.1397981],"iteration":591,"passed_time":0.2790731151,"remaining_time":0.1923341739},
{"learn":[836.7710029],"iteration":592,"passed_time":0.2794406127,"remaining_time":0.1917914492},
{"learn":[836.3185058],"iteration":593,"passed_time":0.2799161935,"remaining_time":0.1913231895},
{"learn":[835.7202942],"iteration":594,"passed_time":0.280438231,"remaining_time":0.190886527},
{"learn":[835.3257831],"iteration":595,"passed_time":0.2807431869,"remaining_time":0.1903024287},
{"learn":[834.8671237],"iteration":596,"passed_time":0.2810668098,"remaining_time":0.1897318666},
{"learn":[834.3585349],"iteration":597,"passed_time":0.2816470139,"remaining_time":0.1893346147},
{"learn":[833.8780023],"iteration":598,"passed_time":0.2822006762,"remaining_time":0.1889189835},
{"learn":[833.5392242],"iteration":599,"passed_time":0.2824925492,"remaining_time":0.1883283661},
{"learn":[833.2766666],"iteration":600,"passed_time":0.2828289219,"remaining_time":0.1877682859},
{"learn":[832.8361116],"iteration":601,"passed_time":0.2832890439,"remaining_time":0.1872907632},
{"learn":[832.4202401],"iteration":602,"passed_time":0.2837264159,"remaining_time":0.1867983203},
{"learn":[831.9829288],"iteration":603,"passed_time":0.2841261212,"remaining_time":0.1862813643},
{"learn":[831.2692277],"iteration":604,"passed_time":0.2846948254,"remaining_time":0.185875134},
{"learn":[830.8891057],"iteration":605,"passed_time":0.2851126976,"remaining_time":0.1853703018},
{"learn":[830.5477245],"iteration":606,"passed_time":0.2854829451,"remaining_time":0.1848349217},
{"learn":[830.5207653],"iteration":607,"passed_time":0.2858423177,"remaining_time":0.1842930733},
{"learn":[829.9296899],"iteration":608,"passed_time":0.286257856,"remaining_time":0.1837878845},
{"learn":[829.5065356],"iteration":609,"passed_time":0.2866400614,"remaining_time":0.1832616786},
{"learn":[829.2698982],"iteration":610,"passed_time":0.2871830158,"remaining_time":0.1828382866},
{"learn":[829.2316482],"iteration":611,"passed_time":0.2875202635,"remaining_time":0.1822840886},
{"learn":[828.7358744],"iteration":612,"passed_time":0.2879711355,"remaining_time":0.1818023319},
{"learn":[828.2901879],"iteration":613,"passed_time":0.2890195874,"remaining_time":0.181696353},
{"learn":[827.9328015],"iteration":614,"passed_time":0.2894060018,"remaining_time":0.1811728629},
{"learn":[827.4511924],"iteration":615,"passed_time":0.2897386666,"remaining_time":0.1806163117},
{"learn":[826.5715503],"iteration":616,"passed_time":0.2904095791,"remaining_time":0.1802704519},
{"learn":[826.5060376],"iteration":617,"passed_time":0.2908632011,"remaining_time":0.1797892279},
{"learn":[826.2474901],"iteration":618,"passed_time":0.291316323,"remaining_time":0.1793077853},
{"learn":[826.2099765],"iteration":619,"passed_time":0.2924481065,"remaining_time":0.1792423878},
{"learn":[825.906133],"iteration":620,"passed_time":0.292815979,"remaining_time":0.1787073366},
{"learn":[825.581762],"iteration":621,"passed_time":0.2932847668,"remaining_time":0.1782341509},
{"learn":[825.5562723],"iteration":622,"passed_time":0.2938116793,"remaining_time":0.1777961526},
{"learn":[825.0433845],"iteration":623,"passed_time":0.2942463844,"remaining_time":0.1773023085},
{"learn":[824.6901532],"iteration":624,"passed_time":0.2947902148,"remaining_time":0.1768741289},
{"learn":[824.2768208],"iteration":625,"passed_time":0.2952178369,"remaining_time":0.1763761517},
{"learn":[824.1783867],"iteration":626,"passed_time":0.2955921674,"remaining_time":0.1758466961},
{"learn":[823.8599556],"iteration":627,"passed_time":0.2960812891,"remaining_time":0.1753857318},
{"learn":[823.5279847],"iteration":628,"passed_time":0.2964097869,"remaining_time":0.1748299379},
{"learn":[823.1889234],"iteration":629,"passed_time":0.296846492,"remaining_time":0.1743384159},
{"learn":[822.6777054],"iteration":630,"passed_time":0.2971716148,"remaining_time":0.1737818159},
{"learn":[822.5382533],"iteration":631,"passed_time":0.2975010296,"remaining_time":0.1732284476},
{"learn":[822.2242093],"iteration":632,"passed_time":0.2979543595,"remaining_time":0.1727476303},
{"learn":[822.2004285],"iteration":633,"passed_time":0.2984571892,"remaining_time":0.1722954751},
{"learn":[821.9154939],"iteration":634,"passed_time":0.2988572285,"remaining_time":0.1717840762},
{"learn":[821.8815836],"iteration":635,"passed_time":0.299384517,"remaining_time":0.1713458556},
{"learn":[821.8338026],"iteration":636,"passed_time":0.2998410969,"remaining_time":0.1708670615},
{"learn":[821.7210961],"iteration":637,"passed_time":0.3002209693,"remaining_time":0.1703448133},
{"learn":[821.6915276],"iteration":638,"passed_time":0.3006063828,"remaining_time":0.1698261411},
{"learn":[821.3265691],"iteration":639,"passed_time":0.3011374212,"remaining_time":0.1693897994},
{"learn":[820.9000713],"iteration":640,"passed_time":0.3015261686,"remaining_time":0.1688734704},
{"learn":[820.3467732],"iteration":641,"passed_time":0.3018559584,"remaining_time":0.1683246622},
{"learn":[820.0201079],"iteration":642,"passed_time":0.3021911231,"remaining_time":0.1677795194},
{"learn":[819.4538472],"iteration":643,"passed_time":0.3025212039,"remaining_time":0.1672322183},
{"learn":[819.4267595],"iteration":644,"passed_time":0.3028766175,"remaining_time":0.1666995337},
{"learn":[818.9904696],"iteration":645,"passed_time":0.3033808222,"remaining_time":0.1662489335},
{"learn":[818.8629368],"iteration":646,"passed_time":0.3037812775,"remaining_time":0.1657415625},
{"learn":[818.8382563],"iteration":647,"passed_time":0.3041705659,"remaining_time":0.1652284555},
{"learn":[818.525444],"iteration":648,"passed_time":0.3046241038,"remaining_time":0.1647504783},
{"learn":[818.1394701],"iteration":649,"passed_time":0.3051068506,"remaining_time":0.1642883042},
{"learn":[817.6902825],"iteration":650,"passed_time":0.3055567646,"remaining_time":0.1638084652},
{"learn":[817.5678535],"iteration":651,"passed_time":0.3061015109,"remaining_time":0.1633793341},
{"learn":[817.5385687],"iteration":652,"passed_time":0.3064895503,"remaining_time":0.1628665757},
{"learn":[817.51284],"iteration":653,"passed_time":0.3070435466,"remaining_time":0.1624419987},
{"learn":[817.1344362],"iteration":654,"passed_time":0.3073964602,"remaining_time":0.1619111126},
{"learn":[816.9190824],"iteration":655,"passed_time":0.3079315817,"remaining_time":0.1614763172},
{"learn":[816.5781639],"iteration":656,"passed_time":0.3084469952,"remaining_time":0.1610309275},
{"learn":[816.5522219],"iteration":657,"passed_time":0.3090017415,"remaining_time":0.1606057684},
{"learn":[816.1170455],"iteration":658,"passed_time":0.3094041558,"remaining_time":0.1601013917},
{"learn":[815.7023712],"iteration":659,"passed_time":0.3097893202,"remaining_time":0.1595884377},
{"learn":[815.6772681],"iteration":660,"passed_time":0.310264942,"remaining_time":0.1591222622},
{"learn":[815.4640649],"iteration":661,"passed_time":0.3106621893,"remaining_time":0.1586160423},
{"learn":[814.9430944],"iteration":662,"passed_time":0.3111458531,"remaining_time":0.1581540762},
{"learn":[814.7506459],"iteration":663,"passed_time":0.3115592663,"remaining_time":0.1576564962},
{"learn":[814.7266106],"iteration":664,"passed_time":0.3120482631,"remaining_time":0.1571972453},
{"learn":[814.2137602],"iteration":665,"passed_time":0.3124167196,"remaining_time":0.156677454},
{"learn":[813.8322435],"iteration":666,"passed_time":0.3127412174,"remaining_time":0.15613617},
{"learn":[813.5173715],"iteration":667,"passed_time":0.3132377561,"remaining_time":0.1556810404},
{"learn":[813.4185756],"iteration":668,"passed_time":0.3135808378,"remaining_time":0.1551498614},
{"learn":[813.0374439],"iteration":669,"passed_time":0.31399771,"remaining_time":0.1546555885},
{"learn":[812.6107013],"iteration":670,"passed_time":0.3143857914,"remaining_time":0.1541474298},
{"learn":[812.3391343],"iteration":671,"passed_time":0.3148379964,"remaining_time":0.1536709268},
{"learn":[812.0483008],"iteration":672,"passed_time":0.3151174945,"remaining_time":0.1531105805},
{"learn":[811.9564558],"iteration":673,"passed_time":0.3156646158,"remaining_time":0.1526805115},
{"learn":[811.690342],"iteration":674,"passed_time":0.3160427383,"remaining_time":0.1521687258},
{"learn":[811.3415854],"iteration":675,"passed_time":0.316385819,"remaining_time":0.1516405405},
{"learn":[811.0672551],"iteration":676,"passed_time":0.3167606085,"remaining_time":0.1511280303},
{"learn":[810.8662317],"iteration":677,"passed_time":0.3171136471,"remaining_time":0.1506055964},
{"learn":[810.5389667],"iteration":678,"passed_time":0.3175308533,"remaining_time":0.1501139969},
{"learn":[810.2976623],"iteration":679,"passed_time":0.3178593921,"remaining_time":0.1495808904},
{"learn":[809.9539057],"iteration":680,"passed_time":0.3184601801,"remaining_time":0.149175914},
{"learn":[809.8334326],"iteration":681,"passed_time":0.3187795529,"remaining_time":0.1486391464},
{"learn":[809.4762692],"iteration":682,"passed_time":0.3191997591,"remaining_time":0.148149815},
{"learn":[809.4384464],"iteration":683,"passed_time":0.3196351312,"remaining_time":0.1476676922},
{"learn":[809.4160217],"iteration":684,"passed_time":0.3201505027,"remaining_time":0.147222494},
{"learn":[809.3957738],"iteration":685,"passed_time":0.320566,"remaining_time":0.1467313761},
{"learn":[809.1117752],"iteration":686,"passed_time":0.321006163,"remaining_time":0.1462517162},
{"learn":[808.9900862],"iteration":687,"passed_time":0.3215377424,"remaining_time":0.1458136274},
{"learn":[808.6815342],"iteration":688,"passed_time":0.3218920321,"remaining_time":0.1452952423},
{"learn":[808.6024587],"iteration":689,"passed_time":0.3221715722,"remaining_time":0.1447437498},
{"learn":[807.7846668],"iteration":690,"passed_time":0.322641944,"remaining_time":0.1442783802},
{"learn":[807.6181811],"iteration":691,"passed_time":0.3231114829,"remaining_time":0.1438126253},
{"learn":[807.2496272],"iteration":692,"passed_time":0.3236676042,"remaining_time":0.1433852157},
{"learn":[807.0524376],"iteration":693,"passed_time":0.323988852,"remaining_time":0.1428538742},
{"learn":[806.7045542],"iteration":694,"passed_time":0.3244777657,"remaining_time":0.1423967173},
{"learn":[806.4506882],"iteration":695,"passed_time":0.3249431376,"remaining_time":0.1419291865},
{"learn":[806.2126097],"iteration":696,"passed_time":0.3254473432,"remaining_time":0.1414785438},
{"learn":[805.7743888],"iteration":697,"passed_time":0.3258044658,"remaining_time":0.1409641099},
{"learn":[805.6632346],"iteration":698,"passed_time":0.3262886706,"remaining_time":0.1405048496},
{"learn":[805.5354891],"iteration":699,"passed_time":0.3267596674,"remaining_time":0.1400398575},
{"learn":[805.3448787],"iteration":700,"passed_time":0.3271917895,"remaining_time":0.1395582669},
{"learn":[804.6792474],"iteration":701,"passed_time":0.3276947032,"remaining_time":0.1391068683},
{"learn":[803.9136225],"iteration":702,"passed_time":0.3282000748,"remaining_time":0.1386563616},
{"learn":[803.5396334],"iteration":703,"passed_time":0.3285501144,"remaining_time":0.138140389},
{"learn":[803.2400371],"iteration":704,"passed_time":0.328912904,"remaining_time":0.1376302222},
{"learn":[803.201187],"iteration":705,"passed_time":0.3294251926,"remaining_time":0.1371827289},
{"learn":[802.8066591],"iteration":706,"passed_time":0.3297351495,"remaining_time":0.1366512006},
{"learn":[802.5446458],"iteration":707,"passed_time":0.3300797722,"remaining_time":0.1361345953},
{"learn":[802.1257188],"iteration":708,"passed_time":0.3305079363,"remaining_time":0.1356527637},
{"learn":[802.045143],"iteration":709,"passed_time":0.3308084753,"remaining_time":0.1351189547},
{"learn":[802.0041759],"iteration":710,"passed_time":0.3311360981,"remaining_time":0.1345968106},
{"learn":[801.5384688],"iteration":711,"passed_time":0.3316838024,"remaining_time":0.1341642347},
{"learn":[801.215801],"iteration":712,"passed_time":0.3320739248,"remaining_time":0.1336679052},
{"learn":[801.0309636],"iteration":713,"passed_time":0.332495006,"remaining_time":0.1331842741},
{"learn":[800.7411462],"iteration":714,"passed_time":0.3330015856,"remaining_time":0.1327348978},
{"learn":[800.3422865],"iteration":715,"passed_time":0.3333745831,"remaining_time":0.1322323765},
{"learn":[799.9546858],"iteration":716,"passed_time":0.3336983309,"remaining_time":0.1317107778},
{"learn":[799.376028],"iteration":717,"passed_time":0.3340807454,"remaining_time":0.1312127719},
{"learn":[798.9991181],"iteration":718,"passed_time":0.3344618268,"remaining_time":0.1307145665},
{"learn":[798.3825922],"iteration":719,"passed_time":0.3348884069,"remaining_time":0.1302343805},
{"learn":[798.1559358],"iteration":720,"passed_time":0.3353907366,"remaining_time":0.1297836553},
{"learn":[797.6866459],"iteration":721,"passed_time":0.3358437755,"remaining_time":0.1293138083},
{"learn":[797.4445356],"iteration":722,"passed_time":0.3363208973,"remaining_time":0.1288532345},
{"learn":[797.1390607],"iteration":723,"passed_time":0.3366562291,"remaining_time":0.1283385625},
{"learn":[797.1171478],"iteration":724,"passed_time":0.337267392,"remaining_time":0.1279290108},
{"learn":[797.0964101],"iteration":725,"passed_time":0.33756939,"remaining_time":0.1274022216},
{"learn":[797.0688148],"iteration":726,"passed_time":0.3380325539,"remaining_time":0.1269365711},
{"learn":[796.9509747],"iteration":727,"passed_time":0.3383830935,"remaining_time":0.1264288481},
{"learn":[796.5887231],"iteration":728,"passed_time":0.3388832572,"remaining_time":0.1259771779},
{"learn":[795.9673041],"iteration":729,"passed_time":0.3392817965,"remaining_time":0.1254877877},
{"learn":[795.925492],"iteration":730,"passed_time":0.3397255435,"remaining_time":0.1250152821},
{"learn":[795.5177698],"iteration":731,"passed_time":0.3400712912,"remaining_time":0.1245069755},
{"learn":[795.5100404],"iteration":732,"passed_time":0.3404422057,"remaining_time":0.1240082796},
{"learn":[794.8217623],"iteration":733,"passed_time":0.3409791181,"remaining_time":0.1235700891},
{"learn":[794.3131037],"iteration":734,"passed_time":0.34144949,"remaining_time":0.1231076392},
{"learn":[794.274642],"iteration":735,"passed_time":0.3418560702,"remaining_time":0.1226222861},
{"learn":[794.2269132],"iteration":736,"passed_time":0.3422766514,"remaining_time":0.1221421429},
{"learn":[793.8490772],"iteration":737,"passed_time":0.342640066,"remaining_time":0.1216418662},
{"learn":[793.6270557],"iteration":738,"passed_time":0.3429662298,"remaining_time":0.1211288038},
{"learn":[793.2027749],"iteration":739,"passed_time":0.3434663514,"remaining_time":0.1206773667},
{"learn":[792.9616605],"iteration":740,"passed_time":0.3438845566,"remaining_time":0.1201971662},
{"learn":[792.4346707],"iteration":741,"passed_time":0.3442632621,"remaining_time":0.1197033984},
{"learn":[791.7200676],"iteration":742,"passed_time":0.3446284266,"remaining_time":0.1192052566},
{"learn":[791.4701719],"iteration":743,"passed_time":0.3450499658,"remaining_time":0.11872687},
{"learn":[790.638278],"iteration":744,"passed_time":0.3453907135,"remaining_time":0.1182209825},
{"learn":[790.2749095],"iteration":745,"passed_time":0.3458521684,"remaining_time":0.1177566364},
{"learn":[789.9382852],"iteration":746,"passed_time":0.3465839135,"remaining_time":0.1173838422},
{"learn":[789.6401327],"iteration":747,"passed_time":0.3469126193,"remaining_time":0.1168743049},
{"learn":[788.9936719],"iteration":748,"passed_time":0.3473499914,"remaining_time":0.116401666},
{"learn":[788.8306995],"iteration":749,"passed_time":0.3477945714,"remaining_time":0.1159315238},
{"learn":[788.5132607],"iteration":750,"passed_time":0.3483456097,"remaining_time":0.1154967468},
{"learn":[787.9419124],"iteration":751,"passed_time":0.3487263152,"remaining_time":0.1150054869},
{"learn":[787.8734407],"iteration":752,"passed_time":0.3492181869,"remaining_time":0.1145509856},
{"learn":[787.7034116],"iteration":753,"passed_time":0.3495690175,"remaining_time":0.1140503691},
{"learn":[787.6674219],"iteration":754,"passed_time":0.3498581816,"remaining_time":0.1135301384},
{"learn":[787.5965645],"iteration":755,"passed_time":0.3502766368,"remaining_time":0.1130522478},
{"learn":[787.058735],"iteration":756,"passed_time":0.3514173791,"remaining_time":0.1128063714},
{"learn":[786.5185912],"iteration":757,"passed_time":0.3517838767,"remaining_time":0.1123109474},
{"learn":[786.5015469],"iteration":758,"passed_time":0.3523061652,"remaining_time":0.1118653304},
{"learn":[786.3596599],"iteration":759,"passed_time":0.3528992862,"remaining_time":0.1114418799},
{"learn":[786.1328428],"iteration":760,"passed_time":0.3535494068,"remaining_time":0.1110358847},
{"learn":[785.5777286],"iteration":761,"passed_time":0.3539044875,"remaining_time":0.1105370971},
{"learn":[785.4799553],"iteration":762,"passed_time":0.3543149437,"remaining_time":0.1100558868},
{"learn":[785.2824675],"iteration":763,"passed_time":0.355010314,"remaining_time":0.1096628719},
{"learn":[784.8655465],"iteration":764,"passed_time":0.3555314765,"remaining_time":0.1092155516},
{"learn":[784.8489572],"iteration":765,"passed_time":0.3558283906,"remaining_time":0.1086995345},
{"learn":[784.2744161],"iteration":766,"passed_time":0.3563466791,"remaining_time":0.108251338},
{"learn":[784.009307],"iteration":767,"passed_time":0.3567021347,"remaining_time":0.1077537699},
{"learn":[783.4158462],"iteration":768,"passed_time":0.3571658396,"remaining_time":0.1072890884},
{"learn":[783.2342104],"iteration":769,"passed_time":0.3582368744,"remaining_time":0.1070058196},
{"learn":[783.1095351],"iteration":770,"passed_time":0.3585739972,"remaining_time":0.1065025231},
{"learn":[783.038714],"iteration":771,"passed_time":0.3589569536,"remaining_time":0.1060131935},
{"learn":[782.693615],"iteration":772,"passed_time":0.3593640759,"remaining_time":0.1055312357},
{"learn":[782.6587274],"iteration":773,"passed_time":0.359941655,"remaining_time":0.1050992429},
{"learn":[782.3337701],"iteration":774,"passed_time":0.3604370687,"remaining_time":0.1046430199},
{"learn":[781.5941979],"iteration":775,"passed_time":0.3608550659,"remaining_time":0.1041643489},
{"learn":[781.5781942],"iteration":776,"passed_time":0.3612382713,"remaining_time":0.1036758488},
{"learn":[781.3058964],"iteration":777,"passed_time":0.3617139771,"remaining_time":0.103214014},
{"learn":[780.8303846],"iteration":778,"passed_time":0.3622879733,"remaining_time":0.1027800284},
{"learn":[780.5461069],"iteration":779,"passed_time":0.3628605114,"remaining_time":0.1023452725},
{"learn":[780.30108],"iteration":780,"passed_time":0.3632588417,"remaining_time":0.1018613141},
{"learn":[780.2653632],"iteration":781,"passed_time":0.3635409649,"remaining_time":0.1013451795},
{"learn":[779.9524009],"iteration":782,"passed_time":0.3639452121,"remaining_time":0.1008634879},
{"learn":[779.6558375],"iteration":783,"passed_time":0.3643740013,"remaining_time":0.1003887555},
{"learn":[778.996315],"iteration":784,"passed_time":0.3649142886,"remaining_time":0.09994467778},
{"learn":[778.9290185],"iteration":785,"passed_time":0.3652399955,"remaining_time":0.09944193261},
{"learn":[778.7970761],"iteration":786,"passed_time":0.3657002424,"remaining_time":0.09897605035},
{"learn":[778.5246625],"iteration":787,"passed_time":0.3661310315,"remaining_time":0.0985022572},
{"learn":[778.1386349],"iteration":788,"passed_time":0.3664927371,"remaining_time":0.09801009825},
{"learn":[778.086353],"iteration":789,"passed_time":0.3667652762,"remaining_time":0.0974945671},
{"learn":[777.9000133],"iteration":790,"passed_time":0.3672064813,"remaining_time":0.09702421566},
{"learn":[777.6545663],"iteration":791,"passed_time":0.3676365204,"remaining_time":0.09655100536},
{"learn":[777.6399417],"iteration":792,"passed_time":0.3680756425,"remaining_time":0.09608027489},
{"learn":[777.3795723],"iteration":793,"passed_time":0.3689127618,"remaining_time":0.0957128828},
{"learn":[776.741383],"iteration":794,"passed_time":0.3694070915,"remaining_time":0.09525591668},
{"learn":[776.6074809],"iteration":795,"passed_time":0.3698547975,"remaining_time":0.09478690791},
{"learn":[776.4339864],"iteration":796,"passed_time":0.3703422113,"remaining_time":0.09432806636},
{"learn":[776.0824569],"iteration":797,"passed_time":0.370824,"remaining_time":0.09386772933},
{"learn":[775.872881],"iteration":798,"passed_time":0.3714529128,"remaining_time":0.09344434978},
{"learn":[775.4069234],"iteration":799,"passed_time":0.3718629101,"remaining_time":0.09296572752},
{"learn":[774.8459246],"iteration":800,"passed_time":0.3721803249,"remaining_time":0.09246427548},
{"learn":[774.7738501],"iteration":801,"passed_time":0.372616489,"remaining_time":0.09199259953},
{"learn":[774.3945661],"iteration":802,"passed_time":0.3730039864,"remaining_time":0.09150907263},
{"learn":[774.1999917],"iteration":803,"passed_time":0.3734159837,"remaining_time":0.09103175721},
{"learn":[773.8515362],"iteration":804,"passed_time":0.3739311052,"remaining_time":0.09057958449},
{"learn":[773.4247755],"iteration":805,"passed_time":0.3743149776,"remaining_time":0.09009566459},
{"learn":[773.1502406],"iteration":806,"passed_time":0.3747663916,"remaining_time":0.0896281457},
{"learn":[773.0556767],"iteration":807,"passed_time":0.3750755145,"remaining_time":0.08912685494},
{"learn":[773.0042327],"iteration":808,"passed_time":0.3755021787,"remaining_time":0.08865379002},
{"learn":[772.9344374],"iteration":809,"passed_time":0.3758543843,"remaining_time":0.0881633741},
{"learn":[772.8388065],"iteration":810,"passed_time":0.3763065483,"remaining_time":0.08769659386},
{"learn":[772.7326238],"iteration":811,"passed_time":0.3767311704,"remaining_time":0.08722347296},
{"learn":[772.7143375],"iteration":812,"passed_time":0.3771976673,"remaining_time":0.08676010306},
{"learn":[772.6672997],"iteration":813,"passed_time":0.3776379973,"remaining_time":0.08629074632},
{"learn":[772.4740479],"iteration":814,"passed_time":0.378135328,"remaining_time":0.08583439961},
{"learn":[772.2317283],"iteration":815,"passed_time":0.3784769097,"remaining_time":0.08534283258},
{"learn":[772.0486298],"iteration":816,"passed_time":0.378740699,"remaining_time":0.08483420797},
{"learn":[772.0342399],"iteration":817,"passed_time":0.3790935296,"remaining_time":0.08434599314},
{"learn":[771.2456336],"iteration":818,"passed_time":0.3795609855,"remaining_time":0.08388344123},
{"learn":[770.9822031],"iteration":819,"passed_time":0.3799472329,"remaining_time":0.08340305112},
{"learn":[770.6605138],"iteration":820,"passed_time":0.3804629374,"remaining_time":0.08295111546},
{"learn":[770.5972542],"iteration":821,"passed_time":0.3808072681,"remaining_time":0.0824619145},
{"learn":[770.5393664],"iteration":822,"passed_time":0.3812940148,"remaining_time":0.08200369456},
{"learn":[770.2183549],"iteration":823,"passed_time":0.3817630957,"remaining_time":0.08154163209},
{"learn":[770.0030246],"iteration":824,"passed_time":0.3822287176,"remaining_time":0.08107881888},
{"learn":[769.798536],"iteration":825,"passed_time":0.3828335465,"remaining_time":0.08064532336},
{"learn":[769.7665371],"iteration":826,"passed_time":0.3833705009,"remaining_time":0.08019721482},
{"learn":[769.7351346],"iteration":827,"passed_time":0.3837218736,"remaining_time":0.07971034089},
{"learn":[769.4399474],"iteration":828,"passed_time":0.3840817462,"remaining_time":0.07922554716},
{"learn":[769.1844527],"iteration":829,"passed_time":0.384557618,"remaining_time":0.07876481332},
{"learn":[768.6226022],"iteration":830,"passed_time":0.3850566566,"remaining_time":0.07830875447},
{"learn":[768.5420019],"iteration":831,"passed_time":0.3854006963,"remaining_time":0.07782129445},
{"learn":[767.9921115],"iteration":832,"passed_time":0.3859834424,"remaining_time":0.07738203467},
{"learn":[767.9052117],"iteration":833,"passed_time":0.3865641055,"remaining_time":0.0769420162},
{"learn":[767.8536931],"iteration":834,"passed_time":0.3869827277,"remaining_time":0.0764696408},
{"learn":[767.8061292],"iteration":835,"passed_time":0.3874251407,"remaining_time":0.0760020611},
{"learn":[767.5555747],"iteration":836,"passed_time":0.3879231794,"remaining_time":0.07554537424},
{"learn":[767.2175407],"iteration":837,"passed_time":0.3882578022,"remaining_time":0.07505699755},
{"learn":[767.2019196],"iteration":838,"passed_time":0.3888056735,"remaining_time":0.07460990874},
{"learn":[766.7100373],"iteration":839,"passed_time":0.3893662947,"remaining_time":0.07416500852},
{"learn":[766.4073043],"iteration":840,"passed_time":0.3896678767,"remaining_time":0.07367085897},
{"learn":[766.161036],"iteration":841,"passed_time":0.3901878322,"remaining_time":0.07321814429},
{"learn":[765.9453359],"iteration":842,"passed_time":0.3906983698,"remaining_time":0.07276351608},
{"learn":[765.6041964],"iteration":843,"passed_time":0.3912192003,"remaining_time":0.07231065788},
{"learn":[765.2709637],"iteration":844,"passed_time":0.3915336562,"remaining_time":0.07181978309},
{"learn":[764.6707887],"iteration":845,"passed_time":0.3920971524,"remaining_time":0.07137465895},
{"learn":[764.4304704],"iteration":846,"passed_time":0.3925154416,"remaining_time":0.07090302546},
{"learn":[764.3966969],"iteration":847,"passed_time":0.392906398,"remaining_time":0.07042661851},
{"learn":[764.0086138],"iteration":848,"passed_time":0.3933836858,"remaining_time":0.06996576744},
{"learn":[763.8336532],"iteration":849,"passed_time":0.3938843074,"remaining_time":0.06950899543},
{"learn":[763.5894191],"iteration":850,"passed_time":0.3942571799,"remaining_time":0.06902975301},
{"learn":[763.503476],"iteration":851,"passed_time":0.3947607176,"remaining_time":0.06857345798},
{"learn":[763.2673672],"iteration":852,"passed_time":0.3953091719,"remaining_time":0.06812479281},
{"learn":[762.9735216],"iteration":853,"passed_time":0.3957608779,"remaining_time":0.06765935383},
{"learn":[762.9578254],"iteration":854,"passed_time":0.396032917,"remaining_time":0.06716347716},
{"learn":[762.8033387],"iteration":855,"passed_time":0.396639913,"remaining_time":0.06672447134},
{"learn":[762.6087022],"iteration":856,"passed_time":0.397088952,"remaining_time":0.0662587166},
{"learn":[762.0717096],"iteration":857,"passed_time":0.3976918649,"remaining_time":0.06581846715},
{"learn":[761.9383695],"iteration":858,"passed_time":0.3982617771,"remaining_time":0.06537242208},
{"learn":[761.4876579],"iteration":859,"passed_time":0.398721566,"remaining_time":0.06490816191},
{"learn":[761.4535466],"iteration":860,"passed_time":0.3990643557,"remaining_time":0.06442502374},
{"learn":[761.4353182],"iteration":861,"passed_time":0.399473853,"remaining_time":0.06395289061},
{"learn":[761.3622741],"iteration":862,"passed_time":0.3998399755,"remaining_time":0.06347401697},
{"learn":[761.0509128],"iteration":863,"passed_time":0.4003088884,"remaining_time":0.06301158428},
{"learn":[760.9888726],"iteration":864,"passed_time":0.4007256356,"remaining_time":0.06254099515},
{"learn":[760.7218705],"iteration":865,"passed_time":0.4011760076,"remaining_time":0.06207573327},
{"learn":[760.4718175],"iteration":866,"passed_time":0.4016398794,"remaining_time":0.06161257666},
{"learn":[760.1583924],"iteration":867,"passed_time":0.4023218329,"remaining_time":0.06118258288},
{"learn":[760.1404659],"iteration":868,"passed_time":0.4028734122,"remaining_time":0.06073235557},
{"learn":[759.9553226],"iteration":869,"passed_time":0.4035631995,"remaining_time":0.06030254706},
{"learn":[759.7413255],"iteration":870,"passed_time":0.4041710705,"remaining_time":0.05986000929},
{"learn":[759.7083599],"iteration":871,"passed_time":0.4048519409,"remaining_time":0.05942780784},
{"learn":[759.4464849],"iteration":872,"passed_time":0.4054267711,"remaining_time":0.05897961045},
{"learn":[759.2889673],"iteration":873,"passed_time":0.4059111428,"remaining_time":0.05851808237},
{"learn":[759.0512127],"iteration":874,"passed_time":0.4063115571,"remaining_time":0.05804450816},
{"learn":[759.0342501],"iteration":875,"passed_time":0.406625055,"remaining_time":0.05755879774},
{"learn":[758.5470307],"iteration":876,"passed_time":0.4072099261,"remaining_time":0.05711154038},
{"learn":[758.0089724],"iteration":877,"passed_time":0.4077218397,"remaining_time":0.05665383194},
{"learn":[757.8529365],"iteration":878,"passed_time":0.4082102114,"remaining_time":0.05619275948},
{"learn":[757.788094],"iteration":879,"passed_time":0.4095320775,"remaining_time":0.0558452833},
{"learn":[757.6702782],"iteration":880,"passed_time":0.4099212409,"remaining_time":0.05536961143},
{"learn":[757.6597707],"iteration":881,"passed_time":0.4111227329,"remaining_time":0.0550028146},
{"learn":[757.0610494],"iteration":882,"passed_time":0.4116013547,"remaining_time":0.05453834484},
{"learn":[756.9843113],"iteration":883,"passed_time":0.4120475177,"remaining_time":0.05406958377},
{"learn":[756.9678193],"iteration":884,"passed_time":0.412439848,"remaining_time":0.05359387856},
{"learn":[756.9556617],"iteration":885,"passed_time":0.4128227625,"remaining_time":0.05311715002},
{"learn":[756.6805985],"iteration":886,"passed_time":0.4134730081,"remaining_time":0.05267468987},
{"learn":[756.2689889],"iteration":887,"passed_time":0.4138875473,"remaining_time":0.052202033},
{"learn":[755.8614368],"iteration":888,"passed_time":0.4143283364,"remaining_time":0.05173278441},
{"learn":[755.4290257],"iteration":889,"passed_time":0.4147033759,"remaining_time":0.05125547342},
{"learn":[755.1239358],"iteration":890,"passed_time":0.4151472479,"remaining_time":0.05078681259},
{"learn":[754.7367246],"iteration":891,"passed_time":0.4156472035,"remaining_time":0.05032499774},
{"learn":[754.2424358],"iteration":892,"passed_time":0.4162003248,"remaining_time":0.04986946781},
{"learn":[754.1493983],"iteration":893,"passed_time":0.4168855702,"remaining_time":0.04942938529},
{"learn":[753.8838018],"iteration":894,"passed_time":0.4174441085,"remaining_time":0.04897388982},
{"learn":[753.4607005],"iteration":895,"passed_time":0.4178848145,"remaining_time":0.0485044874},
{"learn":[753.2673613],"iteration":896,"passed_time":0.4183396455,"remaining_time":0.04803677089},
{"learn":[753.2598403],"iteration":897,"passed_time":0.4191316402,"remaining_time":0.04760738006},
{"learn":[753.0091727],"iteration":898,"passed_time":0.4198380524,"remaining_time":0.04716756763},
{"learn":[752.9388033],"iteration":899,"passed_time":0.4203703409,"remaining_time":0.04670781565},
{"learn":[752.7216103],"iteration":900,"passed_time":0.4208121719,"remaining_time":0.0462379634},
{"learn":[752.7097721],"iteration":901,"passed_time":0.4213271685,"remaining_time":0.04577612252},
{"learn":[752.4161128],"iteration":902,"passed_time":0.42184479,"remaining_time":0.04531444588},
{"learn":[752.3806975],"iteration":903,"passed_time":0.4221647878,"remaining_time":0.04483165889},
{"learn":[751.8933621],"iteration":904,"passed_time":0.4226882843,"remaining_time":0.04437059338},
{"learn":[751.8728744],"iteration":905,"passed_time":0.4230760317,"remaining_time":0.04389530572},
{"learn":[751.8589628],"iteration":906,"passed_time":0.4234539042,"remaining_time":0.04341919856},
{"learn":[751.8315211],"iteration":907,"passed_time":0.4238879423,"remaining_time":0.04294899856},
{"learn":[751.8177375],"iteration":908,"passed_time":0.4242648978,"remaining_time":0.04247316358},
{"learn":[751.7059694],"iteration":909,"passed_time":0.4245843126,"remaining_time":0.04199185509},
{"learn":[751.3012745],"iteration":910,"passed_time":0.4249309353,"remaining_time":0.04151356009},
{"learn":[750.7701047],"iteration":911,"passed_time":0.4254040571,"remaining_time":0.0410477599},
{"learn":[750.7361701],"iteration":912,"passed_time":0.4259479285,"remaining_time":0.04058868541},
{"learn":[750.220982],"iteration":913,"passed_time":0.4262755093,"remaining_time":0.04010907418},
{"learn":[749.9994876],"iteration":914,"passed_time":0.4267500061,"remaining_time":0.03964344319},
{"learn":[749.7350738],"iteration":915,"passed_time":0.4272466688,"remaining_time":0.03917982552},
{"learn":[749.4989732],"iteration":916,"passed_time":0.4276390821,"remaining_time":0.03870669991},
{"learn":[749.4879965],"iteration":917,"passed_time":0.428264536,"remaining_time":0.03825456639},
{"learn":[748.9529767],"iteration":918,"passed_time":0.4287126989,"remaining_time":0.0377864294},
{"learn":[748.7770904],"iteration":919,"passed_time":0.4291032383,"remaining_time":0.03731332507},
{"learn":[748.6948322],"iteration":920,"passed_time":0.4295395274,"remaining_time":0.03684432428},
{"learn":[748.573246],"iteration":921,"passed_time":0.4299878994,"remaining_time":0.03637641665},
{"learn":[748.554901],"iteration":922,"passed_time":0.4303772718,"remaining_time":0.03590362939},
{"learn":[748.4399795],"iteration":923,"passed_time":0.4309856427,"remaining_time":0.03544903555},
{"learn":[748.2837362],"iteration":924,"passed_time":0.4313115985,"remaining_time":0.03497121069},
{"learn":[748.1373313],"iteration":925,"passed_time":0.4316737621,"remaining_time":0.03449660734},
{"learn":[748.1156933],"iteration":926,"passed_time":0.4320471346,"remaining_time":0.03402312926},
{"learn":[747.9041726],"iteration":927,"passed_time":0.4325107975,"remaining_time":0.03355687222},
{"learn":[747.5011498],"iteration":928,"passed_time":0.4329728364,"remaining_time":0.03309049665},
{"learn":[747.1158197],"iteration":929,"passed_time":0.4334635421,"remaining_time":0.03262628811},
{"learn":[746.9043733],"iteration":930,"passed_time":0.4340099974,"remaining_time":0.03216615448},
{"learn":[746.6149896],"iteration":931,"passed_time":0.4346047844,"remaining_time":0.03170936196},
{"learn":[746.3533447],"iteration":932,"passed_time":0.4352867379,"remaining_time":0.03125853316},
{"learn":[746.3309205],"iteration":933,"passed_time":0.4359448995,"remaining_time":0.03080552823},
{"learn":[745.8812387],"iteration":934,"passed_time":0.43660377,"remaining_time":0.03035213375},
{"learn":[745.8683274],"iteration":935,"passed_time":0.4371608083,"remaining_time":0.02989133732},
{"learn":[745.8297732],"iteration":936,"passed_time":0.4375814305,"remaining_time":0.02942116342},
{"learn":[745.5453058],"iteration":937,"passed_time":0.4380579693,"remaining_time":0.02895479115},
{"learn":[745.2032751],"iteration":938,"passed_time":0.4386054656,"remaining_time":0.02849300682},
{"learn":[745.1307037],"iteration":939,"passed_time":0.439146004,"remaining_time":0.028030596},
{"learn":[744.5319562],"iteration":940,"passed_time":0.4401341634,"remaining_time":0.02759608463},
{"learn":[744.4216623],"iteration":941,"passed_time":0.4405077019,"remaining_time":0.02712255489},
{"learn":[744.163842],"iteration":942,"passed_time":0.4409268241,"remaining_time":0.02665199255},
{"learn":[744.1035381],"iteration":943,"passed_time":0.4413009046,"remaining_time":0.02617886722},
{"learn":[744.0909348],"iteration":944,"passed_time":0.4417585265,"remaining_time":0.02571081371},
{"learn":[743.7869319],"iteration":945,"passed_time":0.4420981082,"remaining_time":0.02523604423},
{"learn":[743.7655498],"iteration":946,"passed_time":0.4424608978,"remaining_time":0.02476285912},
{"learn":[743.5026042],"iteration":947,"passed_time":0.4429040618,"remaining_time":0.02429431563},
{"learn":[743.4349871],"iteration":948,"passed_time":0.4433748507,"remaining_time":0.0238273102},
{"learn":[743.135998],"iteration":949,"passed_time":0.4436671407,"remaining_time":0.02335090214},
{"learn":[743.0765794],"iteration":950,"passed_time":0.4439051391,"remaining_time":0.02287208393},
{"learn":[743.0562667],"iteration":951,"passed_time":0.444218262,"remaining_time":0.02239755943},
{"learn":[742.8538634],"iteration":952,"passed_time":0.4445661347,"remaining_time":0.02192508744},
{"learn":[742.735209],"iteration":953,"passed_time":0.444966049,"remaining_time":0.02145538601},
{"learn":[742.4394737],"iteration":954,"passed_time":0.4452775469,"remaining_time":0.02098166451},
{"learn":[742.0720126],"iteration":955,"passed_time":0.4456291695,"remaining_time":0.02051012914},
{"learn":[741.3084705],"iteration":956,"passed_time":0.4459447094,"remaining_time":0.0200372231},
{"learn":[741.0141136],"iteration":957,"passed_time":0.4463869565,"remaining_time":0.0195702006},
{"learn":[740.4847386],"iteration":958,"passed_time":0.4469404938,"remaining_time":0.01910798774},
{"learn":[740.2770792],"iteration":959,"passed_time":0.4474351154,"remaining_time":0.01864312981},
{"learn":[740.0507897],"iteration":960,"passed_time":0.4478834464,"remaining_time":0.01817633133},
{"learn":[739.8649033],"iteration":961,"passed_time":0.4483110276,"remaining_time":0.01770875161},
{"learn":[739.7247082],"iteration":962,"passed_time":0.4488300651,"remaining_time":0.01724476886},
{"learn":[739.4425611],"iteration":963,"passed_time":0.4491852297,"remaining_time":0.01677455215},
{"learn":[739.0251528],"iteration":964,"passed_time":0.4495688941,"remaining_time":0.01630560756},
{"learn":[738.6303595],"iteration":965,"passed_time":0.4500828077,"remaining_time":0.01584142387},
{"learn":[738.3747666],"iteration":966,"passed_time":0.4505476796,"remaining_time":0.01537546373},
{"learn":[737.8524507],"iteration":967,"passed_time":0.4509181771,"remaining_time":0.01490638602},
{"learn":[737.6440444],"iteration":968,"passed_time":0.4514242567,"remaining_time":0.01444184929},
{"learn":[737.0281646],"iteration":969,"passed_time":0.451818587,"remaining_time":0.01397377073},
{"learn":[736.7068832],"iteration":970,"passed_time":0.4522001265,"remaining_time":0.01350546207},
{"learn":[736.6931823],"iteration":971,"passed_time":0.452572957,"remaining_time":0.01303708107},
{"learn":[736.6332486],"iteration":972,"passed_time":0.4529675793,"remaining_time":0.01256950117},
{"learn":[736.2613673],"iteration":973,"passed_time":0.453468618,"remaining_time":0.01210491177},
{"learn":[736.0245146],"iteration":974,"passed_time":0.4538788242,"remaining_time":0.01163791857},
{"learn":[735.9975773],"iteration":975,"passed_time":0.4541066557,"remaining_time":0.01116655711},
{"learn":[735.877948],"iteration":976,"passed_time":0.4544251956,"remaining_time":0.01069782958},
{"learn":[735.8637615],"iteration":977,"passed_time":0.4549076923,"remaining_time":0.01023309737},
{"learn":[735.6183977],"iteration":978,"passed_time":0.4553379815,"remaining_time":0.009767209},
{"learn":[735.1576622],"iteration":979,"passed_time":0.4556736042,"remaining_time":0.00929946131},
{"learn":[735.1333315],"iteration":980,"passed_time":0.4559650603,"remaining_time":0.008831127569},
{"learn":[734.7358832],"iteration":981,"passed_time":0.45644264,"remaining_time":0.008366565704},
{"learn":[734.7085217],"iteration":982,"passed_time":0.4573832587,"remaining_time":0.007909985146},
{"learn":[734.357783],"iteration":983,"passed_time":0.4578618805,"remaining_time":0.007444908627},
{"learn":[733.9330063],"iteration":984,"passed_time":0.458240503,"remaining_time":0.006978281772},
{"learn":[733.8710581],"iteration":985,"passed_time":0.4585661678,"remaining_time":0.00651108149},
{"learn":[733.482242],"iteration":986,"passed_time":0.4591473309,"remaining_time":0.006047533234},
{"learn":[733.1933187],"iteration":987,"passed_time":0.459432121,"remaining_time":0.005580147219},
{"learn":[732.8432483],"iteration":988,"passed_time":0.4597793687,"remaining_time":0.005113825132},
{"learn":[732.7462242],"iteration":989,"passed_time":0.460186616,"remaining_time":0.004648349656},
{"learn":[732.6916431],"iteration":990,"passed_time":0.4605149467,"remaining_time":0.004182274996},
{"learn":[732.6478554],"iteration":991,"passed_time":0.4609717767,"remaining_time":0.003717514328},
{"learn":[732.5194854],"iteration":992,"passed_time":0.4615348979,"remaining_time":0.003253518918},
{"learn":[732.3019491],"iteration":993,"passed_time":0.4619351042,"remaining_time":0.002788340669},
{"learn":[731.9397925],"iteration":994,"passed_time":0.4622777269,"remaining_time":0.002323003653},
{"learn":[731.8770929],"iteration":995,"passed_time":0.4628333482,"remaining_time":0.001858768467},
{"learn":[731.4268978],"iteration":996,"passed_time":0.4633610947,"remaining_time":0.001394266082},
{"learn":[731.3818435],"iteration":997,"passed_time":0.4637414251,"remaining_time":0.0009293415333},
{"learn":[731.2096523],"iteration":998,"passed_time":0.4641640893,"remaining_time":0.000464628718},
{"learn":[731.1965691],"iteration":999,"passed_time":0.46465117,"remaining_time":0}
]}